[
  {
    "reward_call": 1,
    "index": 0,
    "score": -0.84,
    "task_id": "bottle_cage_bike",
    "code_chars": 6180,
    "cadforge_build": 0.0,
    "cadforge_total": -1.0,
    "has_fixture": false,
    "has_cadquery_import": true,
    "error_kind": "SyntaxError"
  },
  {
    "reward_call": 1,
    "index": 1,
    "score": -0.6649999999999999,
    "task_id": "bottle_cage_bike",
    "code_chars": 5944,
    "cadforge_build": 0.0,
    "cadforge_total": -1.0,
    "has_fixture": true,
    "has_cadquery_import": true,
    "error_kind": "SyntaxError"
  },
  {
    "reward_call": 1,
    "index": 2,
    "score": -0.565,
    "task_id": "pipe_clamp_saddle",
    "code_chars": 4746,
    "cadforge_build": 0.0,
    "cadforge_total": -1.0,
    "has_fixture": true,
    "has_cadquery_import": true,
    "error_kind": "TypeError"
  },
  {
    "reward_call": 1,
    "index": 3,
    "score": 0.770444555010733,
    "task_id": "pipe_clamp_saddle",
    "code_chars": 6153,
    "cadforge_build": 1.0,
    "cadforge_total": 0.7299347706008623,
    "has_fixture": true,
    "has_cadquery_import": true,
    "error_kind": "build_ok"
  },
  {
    "reward_call": 2,
    "index": 0,
    "score": 0.8845503697602638,
    "task_id": "table_six_leg_500n",
    "code_chars": 5131,
    "cadforge_build": 1.0,
    "cadforge_total": 0.8641769056003104,
    "has_fixture": true,
    "has_cadquery_import": true,
    "error_kind": "build_ok"
  },
  {
    "reward_call": 2,
    "index": 1,
    "score": -0.565,
    "task_id": "table_six_leg_500n",
    "code_chars": 6073,
    "cadforge_build": 0.0,
    "cadforge_total": -1.0,
    "has_fixture": true,
    "has_cadquery_import": true,
    "error_kind": "unknown"
  },
  {
    "reward_call": 2,
    "index": 2,
    "score": -0.695,
    "task_id": "robot_gripper_two_finger",
    "code_chars": 4208,
    "cadforge_build": 0.0,
    "cadforge_total": -1.0,
    "has_fixture": true,
    "has_cadquery_import": true,
    "error_kind": "SyntaxError"
  },
  {
    "reward_call": 2,
    "index": 3,
    "score": -0.6649999999999999,
    "task_id": "robot_gripper_two_finger",
    "code_chars": 6186,
    "cadforge_build": 0.0,
    "cadforge_total": -1.0,
    "has_fixture": true,
    "has_cadquery_import": true,
    "error_kind": "SyntaxError"
  },
  {
    "reward_call": 3,
    "index": 0,
    "score": -0.84,
    "task_id": "bike_accessory_mount_120n",
    "code_chars": 6128,
    "cadforge_build": 0.0,
    "cadforge_total": -1.0,
    "has_fixture": true,
    "has_cadquery_import": true,
    "error_kind": "SyntaxError"
  },
  {
    "reward_call": 3,
    "index": 1,
    "score": -0.6649999999999999,
    "task_id": "bike_accessory_mount_120n",
    "code_chars": 6274,
    "cadforge_build": 0.0,
    "cadforge_total": -1.0,
    "has_fixture": true,
    "has_cadquery_import": true,
    "error_kind": "SyntaxError"
  },
  {
    "reward_call": 3,
    "index": 2,
    "score": 0.7981208947102704,
    "task_id": "laptop_riser_vented",
    "code_chars": 3990,
    "cadforge_build": 1.0,
    "cadforge_total": 0.7624951702473769,
    "has_fixture": true,
    "has_cadquery_import": true,
    "error_kind": "build_ok"
  },
  {
    "reward_call": 3,
    "index": 3,
    "score": -0.84,
    "task_id": "laptop_riser_vented",
    "code_chars": 5472,
    "cadforge_build": 0.0,
    "cadforge_total": -1.0,
    "has_fixture": false,
    "has_cadquery_import": true,
    "error_kind": "SyntaxError"
  },
  {
    "reward_call": 4,
    "index": 0,
    "score": -0.84,
    "task_id": "bench_vise_simplified",
    "code_chars": 5334,
    "cadforge_build": 0.0,
    "cadforge_total": -1.0,
    "has_fixture": false,
    "has_cadquery_import": true,
    "error_kind": "SyntaxError"
  },
  {
    "reward_call": 4,
    "index": 1,
    "score": -0.84,
    "task_id": "bench_vise_simplified",
    "code_chars": 5572,
    "cadforge_build": 0.0,
    "cadforge_total": -1.0,
    "has_fixture": false,
    "has_cadquery_import": true,
    "error_kind": "SyntaxError"
  },
  {
    "reward_call": 4,
    "index": 2,
    "score": 0.6571400489319114,
    "task_id": "desk_lamp_arm_joint",
    "code_chars": 5885,
    "cadforge_build": 1.0,
    "cadforge_total": 0.5966353516846016,
    "has_fixture": true,
    "has_cadquery_import": true,
    "error_kind": "build_ok"
  },
  {
    "reward_call": 4,
    "index": 3,
    "score": -0.84,
    "task_id": "desk_lamp_arm_joint",
    "code_chars": 5805,
    "cadforge_build": 0.0,
    "cadforge_total": -1.0,
    "has_fixture": false,
    "has_cadquery_import": true,
    "error_kind": "SyntaxError"
  },
  {
    "reward_call": 5,
    "index": 0,
    "score": -0.74,
    "task_id": "ergonomic_curvy_chair_1000n",
    "code_chars": 5169,
    "cadforge_build": 0.0,
    "cadforge_total": -1.0,
    "has_fixture": false,
    "has_cadquery_import": true,
    "error_kind": "TypeError"
  },
  {
    "reward_call": 5,
    "index": 1,
    "score": -0.84,
    "task_id": "ergonomic_curvy_chair_1000n",
    "code_chars": 5408,
    "cadforge_build": 0.0,
    "cadforge_total": -1.0,
    "has_fixture": false,
    "has_cadquery_import": true,
    "error_kind": "SyntaxError"
  },
  {
    "reward_call": 5,
    "index": 2,
    "score": -0.645,
    "task_id": "lightweight_truss_support_250n",
    "code_chars": 4484,
    "cadforge_build": 0.0,
    "cadforge_total": -1.0,
    "has_fixture": true,
    "has_cadquery_import": true,
    "error_kind": "AttributeError"
  },
  {
    "reward_call": 5,
    "index": 3,
    "score": -0.61,
    "task_id": "lightweight_truss_support_250n",
    "code_chars": 3554,
    "cadforge_build": 0.0,
    "cadforge_total": -1.0,
    "has_fixture": true,
    "has_cadquery_import": true,
    "error_kind": "ValueError"
  },
  {
    "reward_call": 6,
    "index": 0,
    "score": -0.84,
    "task_id": "gearbox_housing_split",
    "code_chars": 5514,
    "cadforge_build": 0.0,
    "cadforge_total": -1.0,
    "has_fixture": false,
    "has_cadquery_import": true,
    "error_kind": "SyntaxError"
  },
  {
    "reward_call": 6,
    "index": 1,
    "score": -0.865,
    "task_id": "gearbox_housing_split",
    "code_chars": 5454,
    "cadforge_build": 0.0,
    "cadforge_total": -1.0,
    "has_fixture": false,
    "has_cadquery_import": true,
    "error_kind": "AttributeError"
  },
  {
    "reward_call": 6,
    "index": 2,
    "score": -0.6649999999999999,
    "task_id": "cable_clip_snap",
    "code_chars": 4792,
    "cadforge_build": 0.0,
    "cadforge_total": -1.0,
    "has_fixture": true,
    "has_cadquery_import": true,
    "error_kind": "SyntaxError"
  },
  {
    "reward_call": 6,
    "index": 3,
    "score": -0.84,
    "task_id": "cable_clip_snap",
    "code_chars": 5814,
    "cadforge_build": 0.0,
    "cadforge_total": -1.0,
    "has_fixture": false,
    "has_cadquery_import": true,
    "error_kind": "SyntaxError"
  },
  {
    "reward_call": 7,
    "index": 0,
    "score": -0.84,
    "task_id": "folding_step_stool",
    "code_chars": 6285,
    "cadforge_build": 0.0,
    "cadforge_total": -1.0,
    "has_fixture": false,
    "has_cadquery_import": true,
    "error_kind": "SyntaxError"
  },
  {
    "reward_call": 7,
    "index": 1,
    "score": -0.84,
    "task_id": "folding_step_stool",
    "code_chars": 5364,
    "cadforge_build": 0.0,
    "cadforge_total": -1.0,
    "has_fixture": false,
    "has_cadquery_import": true,
    "error_kind": "SyntaxError"
  },
  {
    "reward_call": 7,
    "index": 2,
    "score": 0.6945054503947041,
    "task_id": "shelf_bracket_triangular_200n",
    "code_chars": 3450,
    "cadforge_build": 1.0,
    "cadforge_total": 0.6405946475231813,
    "has_fixture": true,
    "has_cadquery_import": true,
    "error_kind": "build_ok"
  },
  {
    "reward_call": 7,
    "index": 3,
    "score": -0.565,
    "task_id": "shelf_bracket_triangular_200n",
    "code_chars": 3749,
    "cadforge_build": 0.0,
    "cadforge_total": -1.0,
    "has_fixture": true,
    "has_cadquery_import": true,
    "error_kind": "TypeError"
  },
  {
    "reward_call": 8,
    "index": 0,
    "score": -0.565,
    "task_id": "phone_stand_adjustable_hinge",
    "code_chars": 4750,
    "cadforge_build": 0.0,
    "cadforge_total": -1.0,
    "has_fixture": true,
    "has_cadquery_import": true,
    "error_kind": "ValueError"
  },
  {
    "reward_call": 8,
    "index": 1,
    "score": 0.8989119400703898,
    "task_id": "phone_stand_adjustable_hinge",
    "code_chars": 4176,
    "cadforge_build": 1.0,
    "cadforge_total": 0.8810728706710468,
    "has_fixture": true,
    "has_cadquery_import": true,
    "error_kind": "build_ok"
  },
  {
    "reward_call": 8,
    "index": 2,
    "score": -0.565,
    "task_id": "micro_drone_frame",
    "code_chars": 5268,
    "cadforge_build": 0.0,
    "cadforge_total": -1.0,
    "has_fixture": true,
    "has_cadquery_import": true,
    "error_kind": "TypeError"
  },
  {
    "reward_call": 8,
    "index": 3,
    "score": -0.84,
    "task_id": "micro_drone_frame",
    "code_chars": 5917,
    "cadforge_build": 0.0,
    "cadforge_total": -1.0,
    "has_fixture": false,
    "has_cadquery_import": true,
    "error_kind": "SyntaxError"
  },
  {
    "reward_call": 9,
    "index": 0,
    "score": -0.6649999999999999,
    "task_id": "wall_j_hook_120n",
    "code_chars": 3619,
    "cadforge_build": 0.0,
    "cadforge_total": -1.0,
    "has_fixture": true,
    "has_cadquery_import": true,
    "error_kind": "SyntaxError"
  },
  {
    "reward_call": 9,
    "index": 1,
    "score": -0.565,
    "task_id": "wall_j_hook_120n",
    "code_chars": 4369,
    "cadforge_build": 0.0,
    "cadforge_total": -1.0,
    "has_fixture": true,
    "has_cadquery_import": true,
    "error_kind": "TypeError"
  },
  {
    "reward_call": 9,
    "index": 2,
    "score": -0.565,
    "task_id": "drawer_handle_two_bolt",
    "code_chars": 3920,
    "cadforge_build": 0.0,
    "cadforge_total": -1.0,
    "has_fixture": true,
    "has_cadquery_import": true,
    "error_kind": "TypeError"
  },
  {
    "reward_call": 9,
    "index": 3,
    "score": 0.7152374233607848,
    "task_id": "drawer_handle_two_bolt",
    "code_chars": 2282,
    "cadforge_build": 1.0,
    "cadforge_total": 0.6649852039538644,
    "has_fixture": true,
    "has_cadquery_import": true,
    "error_kind": "build_ok"
  },
  {
    "reward_call": 10,
    "index": 0,
    "score": -0.84,
    "task_id": "shaft_torque_clamp_120nm",
    "code_chars": 5215,
    "cadforge_build": 0.0,
    "cadforge_total": -1.0,
    "has_fixture": true,
    "has_cadquery_import": true,
    "error_kind": "SyntaxError"
  },
  {
    "reward_call": 10,
    "index": 1,
    "score": -0.615,
    "task_id": "shaft_torque_clamp_120nm",
    "code_chars": 5209,
    "cadforge_build": 0.0,
    "cadforge_total": -1.0,
    "has_fixture": true,
    "has_cadquery_import": true,
    "error_kind": "NameError"
  },
  {
    "reward_call": 10,
    "index": 2,
    "score": -0.595,
    "task_id": "hinge_leaf_barrel",
    "code_chars": 4837,
    "cadforge_build": 0.0,
    "cadforge_total": -1.0,
    "has_fixture": true,
    "has_cadquery_import": true,
    "error_kind": "BRep_API"
  },
  {
    "reward_call": 10,
    "index": 3,
    "score": -0.595,
    "task_id": "hinge_leaf_barrel",
    "code_chars": 6057,
    "cadforge_build": 0.0,
    "cadforge_total": -1.0,
    "has_fixture": true,
    "has_cadquery_import": true,
    "error_kind": "ValueError"
  },
  {
    "reward_call": 11,
    "index": 0,
    "score": -0.79,
    "task_id": "ergonomic_curvy_chair_1000n",
    "code_chars": 4883,
    "cadforge_build": 0.0,
    "cadforge_total": -1.0,
    "has_fixture": false,
    "has_cadquery_import": true,
    "error_kind": "AttributeError"
  },
  {
    "reward_call": 11,
    "index": 1,
    "score": -0.84,
    "task_id": "ergonomic_curvy_chair_1000n",
    "code_chars": 5198,
    "cadforge_build": 0.0,
    "cadforge_total": -1.0,
    "has_fixture": false,
    "has_cadquery_import": true,
    "error_kind": "SyntaxError"
  },
  {
    "reward_call": 11,
    "index": 2,
    "score": 0.7985873183029124,
    "task_id": "pipe_clamp_saddle",
    "code_chars": 4307,
    "cadforge_build": 1.0,
    "cadforge_total": 0.7630439038857793,
    "has_fixture": true,
    "has_cadquery_import": true,
    "error_kind": "build_ok"
  },
  {
    "reward_call": 11,
    "index": 3,
    "score": -0.61,
    "task_id": "pipe_clamp_saddle",
    "code_chars": 4098,
    "cadforge_build": 0.0,
    "cadforge_total": -1.0,
    "has_fixture": true,
    "has_cadquery_import": true,
    "error_kind": "unknown"
  },
  {
    "reward_call": 12,
    "index": 0,
    "score": -0.84,
    "task_id": "laptop_riser_vented",
    "code_chars": 5792,
    "cadforge_build": 0.0,
    "cadforge_total": -1.0,
    "has_fixture": false,
    "has_cadquery_import": true,
    "error_kind": "SyntaxError"
  },
  {
    "reward_call": 12,
    "index": 1,
    "score": 0.8229701323180416,
    "task_id": "laptop_riser_vented",
    "code_chars": 4243,
    "cadforge_build": 1.0,
    "cadforge_total": 0.7917295674329902,
    "has_fixture": true,
    "has_cadquery_import": true,
    "error_kind": "build_ok"
  },
  {
    "reward_call": 12,
    "index": 2,
    "score": -0.84,
    "task_id": "gearbox_housing_split",
    "code_chars": 5805,
    "cadforge_build": 0.0,
    "cadforge_total": -1.0,
    "has_fixture": false,
    "has_cadquery_import": true,
    "error_kind": "SyntaxError"
  },
  {
    "reward_call": 12,
    "index": 3,
    "score": -0.84,
    "task_id": "gearbox_housing_split",
    "code_chars": 5905,
    "cadforge_build": 0.0,
    "cadforge_total": -1.0,
    "has_fixture": false,
    "has_cadquery_import": true,
    "error_kind": "SyntaxError"
  },
  {
    "reward_call": 13,
    "index": 0,
    "score": -0.565,
    "task_id": "lightweight_truss_support_250n",
    "code_chars": 3976,
    "cadforge_build": 0.0,
    "cadforge_total": -1.0,
    "has_fixture": true,
    "has_cadquery_import": true,
    "error_kind": "TypeError"
  },
  {
    "reward_call": 13,
    "index": 1,
    "score": -0.8699999999999999,
    "task_id": "lightweight_truss_support_250n",
    "code_chars": 5353,
    "cadforge_build": 0.0,
    "cadforge_total": -1.0,
    "has_fixture": false,
    "has_cadquery_import": true,
    "error_kind": "SyntaxError"
  },
  {
    "reward_call": 13,
    "index": 2,
    "score": 0.5920885416666667,
    "task_id": "wall_j_hook_120n",
    "code_chars": 2571,
    "cadforge_build": 1.0,
    "cadforge_total": 0.5201041666666667,
    "has_fixture": true,
    "has_cadquery_import": true,
    "error_kind": "build_ok"
  },
  {
    "reward_call": 13,
    "index": 3,
    "score": -0.615,
    "task_id": "wall_j_hook_120n",
    "code_chars": 4179,
    "cadforge_build": 0.0,
    "cadforge_total": -1.0,
    "has_fixture": true,
    "has_cadquery_import": true,
    "error_kind": "AttributeError"
  },
  {
    "reward_call": 14,
    "index": 0,
    "score": -0.84,
    "task_id": "desk_lamp_arm_joint",
    "code_chars": 5644,
    "cadforge_build": 0.0,
    "cadforge_total": -1.0,
    "has_fixture": false,
    "has_cadquery_import": true,
    "error_kind": "SyntaxError"
  },
  {
    "reward_call": 14,
    "index": 1,
    "score": -0.84,
    "task_id": "desk_lamp_arm_joint",
    "code_chars": 5694,
    "cadforge_build": 0.0,
    "cadforge_total": -1.0,
    "has_fixture": false,
    "has_cadquery_import": true,
    "error_kind": "SyntaxError"
  },
  {
    "reward_call": 14,
    "index": 2,
    "score": 0.7292988990436297,
    "task_id": "robot_gripper_two_finger",
    "code_chars": 4459,
    "cadforge_build": 1.0,
    "cadforge_total": 0.6815281165219172,
    "has_fixture": true,
    "has_cadquery_import": true,
    "error_kind": "build_ok"
  },
  {
    "reward_call": 14,
    "index": 3,
    "score": -0.6649999999999999,
    "task_id": "robot_gripper_two_finger",
    "code_chars": 5451,
    "cadforge_build": 0.0,
    "cadforge_total": -1.0,
    "has_fixture": true,
    "has_cadquery_import": true,
    "error_kind": "SyntaxError"
  },
  {
    "reward_call": 15,
    "index": 0,
    "score": 0.7945833333333334,
    "task_id": "shelf_bracket_triangular_200n",
    "code_chars": 4031,
    "cadforge_build": 1.0,
    "cadforge_total": 0.7583333333333334,
    "has_fixture": true,
    "has_cadquery_import": true,
    "error_kind": "build_ok"
  },
  {
    "reward_call": 15,
    "index": 1,
    "score": 0.8232339705474382,
    "task_id": "shelf_bracket_triangular_200n",
    "code_chars": 3850,
    "cadforge_build": 1.0,
    "cadforge_total": 0.7920399653499273,
    "has_fixture": true,
    "has_cadquery_import": true,
    "error_kind": "build_ok"
  },
  {
    "reward_call": 15,
    "index": 2,
    "score": -0.84,
    "task_id": "micro_drone_frame",
    "code_chars": 6013,
    "cadforge_build": 0.0,
    "cadforge_total": -1.0,
    "has_fixture": false,
    "has_cadquery_import": true,
    "error_kind": "SyntaxError"
  },
  {
    "reward_call": 15,
    "index": 3,
    "score": -0.84,
    "task_id": "micro_drone_frame",
    "code_chars": 5922,
    "cadforge_build": 0.0,
    "cadforge_total": -1.0,
    "has_fixture": false,
    "has_cadquery_import": true,
    "error_kind": "SyntaxError"
  },
  {
    "reward_call": 16,
    "index": 0,
    "score": -0.595,
    "task_id": "drawer_handle_two_bolt",
    "code_chars": 4798,
    "cadforge_build": 0.0,
    "cadforge_total": -1.0,
    "has_fixture": true,
    "has_cadquery_import": true,
    "error_kind": "unknown"
  },
  {
    "reward_call": 16,
    "index": 1,
    "score": 0.7621206394200344,
    "task_id": "drawer_handle_two_bolt",
    "code_chars": 2362,
    "cadforge_build": 1.0,
    "cadforge_total": 0.7201419287294522,
    "has_fixture": true,
    "has_cadquery_import": true,
    "error_kind": "build_ok"
  },
  {
    "reward_call": 16,
    "index": 2,
    "score": 0.6708019450756568,
    "task_id": "bike_accessory_mount_120n",
    "code_chars": 3691,
    "cadforge_build": 1.0,
    "cadforge_total": 0.6127081706772433,
    "has_fixture": true,
    "has_cadquery_import": true,
    "error_kind": "build_ok"
  },
  {
    "reward_call": 16,
    "index": 3,
    "score": 0.748018455196793,
    "task_id": "bike_accessory_mount_120n",
    "code_chars": 4511,
    "cadforge_build": 1.0,
    "cadforge_total": 0.7035511237609329,
    "has_fixture": true,
    "has_cadquery_import": true,
    "error_kind": "build_ok"
  },
  {
    "reward_call": 17,
    "index": 0,
    "score": -0.595,
    "task_id": "hinge_leaf_barrel",
    "code_chars": 5141,
    "cadforge_build": 0.0,
    "cadforge_total": -1.0,
    "has_fixture": true,
    "has_cadquery_import": true,
    "error_kind": "ValueError"
  },
  {
    "reward_call": 17,
    "index": 1,
    "score": 0.6935120777921006,
    "task_id": "hinge_leaf_barrel",
    "code_chars": 5678,
    "cadforge_build": 1.0,
    "cadforge_total": 0.6394259738730594,
    "has_fixture": true,
    "has_cadquery_import": true,
    "error_kind": "build_ok"
  },
  {
    "reward_call": 17,
    "index": 2,
    "score": -0.84,
    "task_id": "phone_stand_adjustable_hinge",
    "code_chars": 5903,
    "cadforge_build": 0.0,
    "cadforge_total": -1.0,
    "has_fixture": false,
    "has_cadquery_import": true,
    "error_kind": "SyntaxError"
  },
  {
    "reward_call": 17,
    "index": 3,
    "score": 0.8979407835056935,
    "task_id": "phone_stand_adjustable_hinge",
    "code_chars": 3846,
    "cadforge_build": 1.0,
    "cadforge_total": 0.87993033353611,
    "has_fixture": true,
    "has_cadquery_import": true,
    "error_kind": "build_ok"
  },
  {
    "reward_call": 18,
    "index": 0,
    "score": -0.84,
    "task_id": "folding_step_stool",
    "code_chars": 5335,
    "cadforge_build": 0.0,
    "cadforge_total": -1.0,
    "has_fixture": false,
    "has_cadquery_import": true,
    "error_kind": "SyntaxError"
  },
  {
    "reward_call": 18,
    "index": 1,
    "score": -0.84,
    "task_id": "folding_step_stool",
    "code_chars": 5235,
    "cadforge_build": 0.0,
    "cadforge_total": -1.0,
    "has_fixture": false,
    "has_cadquery_import": true,
    "error_kind": "SyntaxError"
  },
  {
    "reward_call": 18,
    "index": 2,
    "score": -0.615,
    "task_id": "table_six_leg_500n",
    "code_chars": 3404,
    "cadforge_build": 0.0,
    "cadforge_total": -1.0,
    "has_fixture": true,
    "has_cadquery_import": true,
    "error_kind": "AttributeError"
  },
  {
    "reward_call": 18,
    "index": 3,
    "score": 0.8017035468139491,
    "task_id": "table_six_leg_500n",
    "code_chars": 5282,
    "cadforge_build": 1.0,
    "cadforge_total": 0.7667100550752342,
    "has_fixture": true,
    "has_cadquery_import": true,
    "error_kind": "build_ok"
  },
  {
    "reward_call": 19,
    "index": 0,
    "score": 0.5738930435982795,
    "task_id": "shaft_torque_clamp_120nm",
    "code_chars": 3560,
    "cadforge_build": 1.0,
    "cadforge_total": 0.4986976983509171,
    "has_fixture": true,
    "has_cadquery_import": true,
    "error_kind": "build_ok"
  },
  {
    "reward_call": 19,
    "index": 1,
    "score": -0.6649999999999999,
    "task_id": "shaft_torque_clamp_120nm",
    "code_chars": 5936,
    "cadforge_build": 0.0,
    "cadforge_total": -1.0,
    "has_fixture": true,
    "has_cadquery_import": true,
    "error_kind": "SyntaxError"
  },
  {
    "reward_call": 19,
    "index": 2,
    "score": -0.565,
    "task_id": "bottle_cage_bike",
    "code_chars": 5253,
    "cadforge_build": 0.0,
    "cadforge_total": -1.0,
    "has_fixture": true,
    "has_cadquery_import": true,
    "error_kind": "TypeError"
  },
  {
    "reward_call": 19,
    "index": 3,
    "score": -0.565,
    "task_id": "bottle_cage_bike",
    "code_chars": 5862,
    "cadforge_build": 0.0,
    "cadforge_total": -1.0,
    "has_fixture": true,
    "has_cadquery_import": true,
    "error_kind": "unknown"
  },
  {
    "reward_call": 20,
    "index": 0,
    "score": -0.71,
    "task_id": "bench_vise_simplified",
    "code_chars": 4991,
    "cadforge_build": 0.0,
    "cadforge_total": -1.0,
    "has_fixture": true,
    "has_cadquery_import": true,
    "error_kind": "SyntaxError"
  },
  {
    "reward_call": 20,
    "index": 1,
    "score": -0.84,
    "task_id": "bench_vise_simplified",
    "code_chars": 5288,
    "cadforge_build": 0.0,
    "cadforge_total": -1.0,
    "has_fixture": false,
    "has_cadquery_import": true,
    "error_kind": "SyntaxError"
  },
  {
    "reward_call": 20,
    "index": 2,
    "score": 0.8406452528509025,
    "task_id": "cable_clip_snap",
    "code_chars": 4185,
    "cadforge_build": 1.0,
    "cadforge_total": 0.8125238268834147,
    "has_fixture": true,
    "has_cadquery_import": true,
    "error_kind": "build_ok"
  },
  {
    "reward_call": 20,
    "index": 3,
    "score": -0.565,
    "task_id": "cable_clip_snap",
    "code_chars": 5716,
    "cadforge_build": 0.0,
    "cadforge_total": -1.0,
    "has_fixture": true,
    "has_cadquery_import": true,
    "error_kind": "BRep_API"
  },
  {
    "reward_call": 21,
    "index": 0,
    "score": -0.565,
    "task_id": "micro_drone_frame",
    "code_chars": 5690,
    "cadforge_build": 0.0,
    "cadforge_total": -1.0,
    "has_fixture": true,
    "has_cadquery_import": true,
    "error_kind": "ValueError"
  },
  {
    "reward_call": 21,
    "index": 1,
    "score": -0.615,
    "task_id": "micro_drone_frame",
    "code_chars": 5600,
    "cadforge_build": 0.0,
    "cadforge_total": -1.0,
    "has_fixture": true,
    "has_cadquery_import": true,
    "error_kind": "NameError"
  },
  {
    "reward_call": 21,
    "index": 2,
    "score": 0.6909928797128871,
    "task_id": "bike_accessory_mount_120n",
    "code_chars": 3893,
    "cadforge_build": 1.0,
    "cadforge_total": 0.636462211426926,
    "has_fixture": true,
    "has_cadquery_import": true,
    "error_kind": "build_ok"
  },
  {
    "reward_call": 21,
    "index": 3,
    "score": -0.615,
    "task_id": "bike_accessory_mount_120n",
    "code_chars": 4698,
    "cadforge_build": 0.0,
    "cadforge_total": -1.0,
    "has_fixture": true,
    "has_cadquery_import": true,
    "error_kind": "AttributeError"
  },
  {
    "reward_call": 22,
    "index": 0,
    "score": -0.84,
    "task_id": "desk_lamp_arm_joint",
    "code_chars": 5290,
    "cadforge_build": 0.0,
    "cadforge_total": -1.0,
    "has_fixture": false,
    "has_cadquery_import": true,
    "error_kind": "SyntaxError"
  },
  {
    "reward_call": 22,
    "index": 1,
    "score": -0.84,
    "task_id": "desk_lamp_arm_joint",
    "code_chars": 6092,
    "cadforge_build": 0.0,
    "cadforge_total": -1.0,
    "has_fixture": false,
    "has_cadquery_import": true,
    "error_kind": "SyntaxError"
  },
  {
    "reward_call": 22,
    "index": 2,
    "score": 0.7858514119963492,
    "task_id": "robot_gripper_two_finger",
    "code_chars": 3520,
    "cadforge_build": 1.0,
    "cadforge_total": 0.7480604847015874,
    "has_fixture": true,
    "has_cadquery_import": true,
    "error_kind": "build_ok"
  },
  {
    "reward_call": 22,
    "index": 3,
    "score": -0.84,
    "task_id": "robot_gripper_two_finger",
    "code_chars": 5443,
    "cadforge_build": 0.0,
    "cadforge_total": -1.0,
    "has_fixture": false,
    "has_cadquery_import": true,
    "error_kind": "SyntaxError"
  },
  {
    "reward_call": 23,
    "index": 0,
    "score": -0.565,
    "task_id": "phone_stand_adjustable_hinge",
    "code_chars": 5380,
    "cadforge_build": 0.0,
    "cadforge_total": -1.0,
    "has_fixture": true,
    "has_cadquery_import": true,
    "error_kind": "TypeError"
  },
  {
    "reward_call": 23,
    "index": 1,
    "score": 0.8120360233537414,
    "task_id": "phone_stand_adjustable_hinge",
    "code_chars": 5196,
    "cadforge_build": 1.0,
    "cadforge_total": 0.778865909827931,
    "has_fixture": true,
    "has_cadquery_import": true,
    "error_kind": "build_ok"
  },
  {
    "reward_call": 23,
    "index": 2,
    "score": -0.6649999999999999,
    "task_id": "pipe_clamp_saddle",
    "code_chars": 3213,
    "cadforge_build": 0.0,
    "cadforge_total": -1.0,
    "has_fixture": true,
    "has_cadquery_import": true,
    "error_kind": "SyntaxError"
  },
  {
    "reward_call": 23,
    "index": 3,
    "score": -0.84,
    "task_id": "pipe_clamp_saddle",
    "code_chars": 5624,
    "cadforge_build": 0.0,
    "cadforge_total": -1.0,
    "has_fixture": false,
    "has_cadquery_import": true,
    "error_kind": "SyntaxError"
  },
  {
    "reward_call": 24,
    "index": 0,
    "score": 0.7216417724094514,
    "task_id": "wall_j_hook_120n",
    "code_chars": 2812,
    "cadforge_build": 1.0,
    "cadforge_total": 0.6725197322464134,
    "has_fixture": true,
    "has_cadquery_import": true,
    "error_kind": "build_ok"
  },
  {
    "reward_call": 24,
    "index": 1,
    "score": -0.615,
    "task_id": "wall_j_hook_120n",
    "code_chars": 4168,
    "cadforge_build": 0.0,
    "cadforge_total": -1.0,
    "has_fixture": true,
    "has_cadquery_import": true,
    "error_kind": "NameError"
  },
  {
    "reward_call": 24,
    "index": 2,
    "score": -0.6649999999999999,
    "task_id": "gearbox_housing_split",
    "code_chars": 5075,
    "cadforge_build": 0.0,
    "cadforge_total": -1.0,
    "has_fixture": true,
    "has_cadquery_import": true,
    "error_kind": "SyntaxError"
  },
  {
    "reward_call": 24,
    "index": 3,
    "score": -0.84,
    "task_id": "gearbox_housing_split",
    "code_chars": 5260,
    "cadforge_build": 0.0,
    "cadforge_total": -1.0,
    "has_fixture": false,
    "has_cadquery_import": true,
    "error_kind": "SyntaxError"
  },
  {
    "reward_call": 25,
    "index": 0,
    "score": -0.84,
    "task_id": "ergonomic_curvy_chair_1000n",
    "code_chars": 5532,
    "cadforge_build": 0.0,
    "cadforge_total": -1.0,
    "has_fixture": false,
    "has_cadquery_import": true,
    "error_kind": "SyntaxError"
  },
  {
    "reward_call": 25,
    "index": 1,
    "score": -0.84,
    "task_id": "ergonomic_curvy_chair_1000n",
    "code_chars": 4912,
    "cadforge_build": 0.0,
    "cadforge_total": -1.0,
    "has_fixture": false,
    "has_cadquery_import": true,
    "error_kind": "SyntaxError"
  },
  {
    "reward_call": 25,
    "index": 2,
    "score": 0.8267267120260791,
    "task_id": "table_six_leg_500n",
    "code_chars": 3063,
    "cadforge_build": 1.0,
    "cadforge_total": 0.7961490729718578,
    "has_fixture": true,
    "has_cadquery_import": true,
    "error_kind": "build_ok"
  },
  {
    "reward_call": 25,
    "index": 3,
    "score": 0.7771561208338964,
    "task_id": "table_six_leg_500n",
    "code_chars": 5640,
    "cadforge_build": 1.0,
    "cadforge_total": 0.7378307303928193,
    "has_fixture": true,
    "has_cadquery_import": true,
    "error_kind": "build_ok"
  },
  {
    "reward_call": 26,
    "index": 0,
    "score": -0.565,
    "task_id": "bottle_cage_bike",
    "code_chars": 5659,
    "cadforge_build": 0.0,
    "cadforge_total": -1.0,
    "has_fixture": true,
    "has_cadquery_import": true,
    "error_kind": "ValueError"
  },
  {
    "reward_call": 26,
    "index": 1,
    "score": 0.814682099431488,
    "task_id": "bottle_cage_bike",
    "code_chars": 4275,
    "cadforge_build": 1.0,
    "cadforge_total": 0.7819789405076328,
    "has_fixture": true,
    "has_cadquery_import": true,
    "error_kind": "build_ok"
  },
  {
    "reward_call": 26,
    "index": 2,
    "score": -0.565,
    "task_id": "laptop_riser_vented",
    "code_chars": 4553,
    "cadforge_build": 0.0,
    "cadforge_total": -1.0,
    "has_fixture": true,
    "has_cadquery_import": true,
    "error_kind": "ValueError"
  },
  {
    "reward_call": 26,
    "index": 3,
    "score": -0.615,
    "task_id": "laptop_riser_vented",
    "code_chars": 4428,
    "cadforge_build": 0.0,
    "cadforge_total": -1.0,
    "has_fixture": true,
    "has_cadquery_import": true,
    "error_kind": "AttributeError"
  },
  {
    "reward_call": 27,
    "index": 0,
    "score": 0.6730844250208622,
    "task_id": "hinge_leaf_barrel",
    "code_chars": 5221,
    "cadforge_build": 1.0,
    "cadforge_total": 0.6153934412010144,
    "has_fixture": true,
    "has_cadquery_import": true,
    "error_kind": "build_ok"
  },
  {
    "reward_call": 27,
    "index": 1,
    "score": -0.8699999999999999,
    "task_id": "hinge_leaf_barrel",
    "code_chars": 5829,
    "cadforge_build": 0.0,
    "cadforge_total": -1.0,
    "has_fixture": false,
    "has_cadquery_import": true,
    "error_kind": "SyntaxError"
  },
  {
    "reward_call": 27,
    "index": 2,
    "score": -0.84,
    "task_id": "cable_clip_snap",
    "code_chars": 5789,
    "cadforge_build": 0.0,
    "cadforge_total": -1.0,
    "has_fixture": false,
    "has_cadquery_import": true,
    "error_kind": "SyntaxError"
  },
  {
    "reward_call": 27,
    "index": 3,
    "score": -0.74,
    "task_id": "cable_clip_snap",
    "code_chars": 5940,
    "cadforge_build": 0.0,
    "cadforge_total": -1.0,
    "has_fixture": false,
    "has_cadquery_import": true,
    "error_kind": "ValueError"
  },
  {
    "reward_call": 28,
    "index": 0,
    "score": -0.84,
    "task_id": "bench_vise_simplified",
    "code_chars": 5124,
    "cadforge_build": 0.0,
    "cadforge_total": -1.0,
    "has_fixture": false,
    "has_cadquery_import": true,
    "error_kind": "SyntaxError"
  },
  {
    "reward_call": 28,
    "index": 1,
    "score": -0.84,
    "task_id": "bench_vise_simplified",
    "code_chars": 5778,
    "cadforge_build": 0.0,
    "cadforge_total": -1.0,
    "has_fixture": false,
    "has_cadquery_import": true,
    "error_kind": "SyntaxError"
  },
  {
    "reward_call": 28,
    "index": 2,
    "score": -0.84,
    "task_id": "folding_step_stool",
    "code_chars": 5592,
    "cadforge_build": 0.0,
    "cadforge_total": -1.0,
    "has_fixture": false,
    "has_cadquery_import": true,
    "error_kind": "SyntaxError"
  },
  {
    "reward_call": 28,
    "index": 3,
    "score": -0.84,
    "task_id": "folding_step_stool",
    "code_chars": 5254,
    "cadforge_build": 0.0,
    "cadforge_total": -1.0,
    "has_fixture": false,
    "has_cadquery_import": true,
    "error_kind": "SyntaxError"
  },
  {
    "reward_call": 29,
    "index": 0,
    "score": 0.7325234226068589,
    "task_id": "drawer_handle_two_bolt",
    "code_chars": 2445,
    "cadforge_build": 1.0,
    "cadforge_total": 0.6853216736551281,
    "has_fixture": true,
    "has_cadquery_import": true,
    "error_kind": "build_ok"
  },
  {
    "reward_call": 29,
    "index": 1,
    "score": -0.595,
    "task_id": "drawer_handle_two_bolt",
    "code_chars": 3497,
    "cadforge_build": 0.0,
    "cadforge_total": -1.0,
    "has_fixture": true,
    "has_cadquery_import": true,
    "error_kind": "TypeError"
  },
  {
    "reward_call": 29,
    "index": 2,
    "score": -0.6649999999999999,
    "task_id": "shaft_torque_clamp_120nm",
    "code_chars": 5372,
    "cadforge_build": 0.0,
    "cadforge_total": -1.0,
    "has_fixture": true,
    "has_cadquery_import": true,
    "error_kind": "SyntaxError"
  },
  {
    "reward_call": 29,
    "index": 3,
    "score": -0.645,
    "task_id": "shaft_torque_clamp_120nm",
    "code_chars": 3407,
    "cadforge_build": 0.0,
    "cadforge_total": -1.0,
    "has_fixture": true,
    "has_cadquery_import": true,
    "error_kind": "NameError"
  },
  {
    "reward_call": 30,
    "index": 0,
    "score": -0.615,
    "task_id": "lightweight_truss_support_250n",
    "code_chars": 4762,
    "cadforge_build": 0.0,
    "cadforge_total": -1.0,
    "has_fixture": true,
    "has_cadquery_import": true,
    "error_kind": "AttributeError"
  },
  {
    "reward_call": 30,
    "index": 1,
    "score": -0.84,
    "task_id": "lightweight_truss_support_250n",
    "code_chars": 5053,
    "cadforge_build": 0.0,
    "cadforge_total": -1.0,
    "has_fixture": false,
    "has_cadquery_import": true,
    "error_kind": "SyntaxError"
  },
  {
    "reward_call": 30,
    "index": 2,
    "score": -0.6649999999999999,
    "task_id": "shelf_bracket_triangular_200n",
    "code_chars": 3097,
    "cadforge_build": 0.0,
    "cadforge_total": -1.0,
    "has_fixture": true,
    "has_cadquery_import": true,
    "error_kind": "SyntaxError"
  },
  {
    "reward_call": 30,
    "index": 3,
    "score": 0.8792378476009259,
    "task_id": "shelf_bracket_triangular_200n",
    "code_chars": 2662,
    "cadforge_build": 1.0,
    "cadforge_total": 0.8579268795305011,
    "has_fixture": true,
    "has_cadquery_import": true,
    "error_kind": "build_ok"
  },
  {
    "reward_call": 31,
    "index": 0,
    "score": -0.6649999999999999,
    "task_id": "desk_lamp_arm_joint",
    "code_chars": 6152,
    "cadforge_build": 0.0,
    "cadforge_total": -1.0,
    "has_fixture": true,
    "has_cadquery_import": true,
    "error_kind": "SyntaxError"
  },
  {
    "reward_call": 31,
    "index": 1,
    "score": -0.565,
    "task_id": "desk_lamp_arm_joint",
    "code_chars": 5784,
    "cadforge_build": 0.0,
    "cadforge_total": -1.0,
    "has_fixture": true,
    "has_cadquery_import": true,
    "error_kind": "TypeError"
  },
  {
    "reward_call": 31,
    "index": 2,
    "score": -0.565,
    "task_id": "robot_gripper_two_finger",
    "code_chars": 3974,
    "cadforge_build": 0.0,
    "cadforge_total": -1.0,
    "has_fixture": true,
    "has_cadquery_import": true,
    "error_kind": "TypeError"
  },
  {
    "reward_call": 31,
    "index": 3,
    "score": 0.8011607142857143,
    "task_id": "robot_gripper_two_finger",
    "code_chars": 4552,
    "cadforge_build": 1.0,
    "cadforge_total": 0.7660714285714286,
    "has_fixture": true,
    "has_cadquery_import": true,
    "error_kind": "build_ok"
  },
  {
    "reward_call": 32,
    "index": 0,
    "score": -0.595,
    "task_id": "pipe_clamp_saddle",
    "code_chars": 3251,
    "cadforge_build": 0.0,
    "cadforge_total": -1.0,
    "has_fixture": true,
    "has_cadquery_import": true,
    "error_kind": "StdFail"
  },
  {
    "reward_call": 32,
    "index": 1,
    "score": -0.84,
    "task_id": "pipe_clamp_saddle",
    "code_chars": 6271,
    "cadforge_build": 0.0,
    "cadforge_total": -1.0,
    "has_fixture": false,
    "has_cadquery_import": true,
    "error_kind": "SyntaxError"
  },
  {
    "reward_call": 32,
    "index": 2,
    "score": -0.61,
    "task_id": "wall_j_hook_120n",
    "code_chars": 4150,
    "cadforge_build": 0.0,
    "cadforge_total": -1.0,
    "has_fixture": true,
    "has_cadquery_import": true,
    "error_kind": "unknown"
  },
  {
    "reward_call": 32,
    "index": 3,
    "score": -0.565,
    "task_id": "wall_j_hook_120n",
    "code_chars": 3835,
    "cadforge_build": 0.0,
    "cadforge_total": -1.0,
    "has_fixture": true,
    "has_cadquery_import": true,
    "error_kind": "ValueError"
  },
  {
    "reward_call": 33,
    "index": 0,
    "score": -0.565,
    "task_id": "laptop_riser_vented",
    "code_chars": 4353,
    "cadforge_build": 0.0,
    "cadforge_total": -1.0,
    "has_fixture": true,
    "has_cadquery_import": true,
    "error_kind": "ValueError"
  },
  {
    "reward_call": 33,
    "index": 1,
    "score": 0.875122259801786,
    "task_id": "laptop_riser_vented",
    "code_chars": 3799,
    "cadforge_build": 1.0,
    "cadforge_total": 0.853085011531513,
    "has_fixture": true,
    "has_cadquery_import": true,
    "error_kind": "build_ok"
  },
  {
    "reward_call": 33,
    "index": 2,
    "score": -0.84,
    "task_id": "bench_vise_simplified",
    "code_chars": 5867,
    "cadforge_build": 0.0,
    "cadforge_total": -1.0,
    "has_fixture": false,
    "has_cadquery_import": true,
    "error_kind": "SyntaxError"
  },
  {
    "reward_call": 33,
    "index": 3,
    "score": -0.84,
    "task_id": "bench_vise_simplified",
    "code_chars": 5434,
    "cadforge_build": 0.0,
    "cadforge_total": -1.0,
    "has_fixture": false,
    "has_cadquery_import": true,
    "error_kind": "SyntaxError"
  },
  {
    "reward_call": 34,
    "index": 0,
    "score": 0.6869166666666668,
    "task_id": "table_six_leg_500n",
    "code_chars": 3276,
    "cadforge_build": 1.0,
    "cadforge_total": 0.6316666666666668,
    "has_fixture": true,
    "has_cadquery_import": true,
    "error_kind": "build_ok"
  },
  {
    "reward_call": 34,
    "index": 1,
    "score": -0.615,
    "task_id": "table_six_leg_500n",
    "code_chars": 3561,
    "cadforge_build": 0.0,
    "cadforge_total": -1.0,
    "has_fixture": true,
    "has_cadquery_import": true,
    "error_kind": "NameError"
  },
  {
    "reward_call": 34,
    "index": 2,
    "score": -0.6649999999999999,
    "task_id": "lightweight_truss_support_250n",
    "code_chars": 5589,
    "cadforge_build": 0.0,
    "cadforge_total": -1.0,
    "has_fixture": true,
    "has_cadquery_import": true,
    "error_kind": "SyntaxError"
  },
  {
    "reward_call": 34,
    "index": 3,
    "score": -0.595,
    "task_id": "lightweight_truss_support_250n",
    "code_chars": 4236,
    "cadforge_build": 0.0,
    "cadforge_total": -1.0,
    "has_fixture": true,
    "has_cadquery_import": true,
    "error_kind": "TypeError"
  },
  {
    "reward_call": 35,
    "index": 0,
    "score": 0.8842360448284298,
    "task_id": "phone_stand_adjustable_hinge",
    "code_chars": 3470,
    "cadforge_build": 1.0,
    "cadforge_total": 0.8638071115628585,
    "has_fixture": true,
    "has_cadquery_import": true,
    "error_kind": "build_ok"
  },
  {
    "reward_call": 35,
    "index": 1,
    "score": 0.9193229814943313,
    "task_id": "phone_stand_adjustable_hinge",
    "code_chars": 5465,
    "cadforge_build": 1.0,
    "cadforge_total": 0.9050858605815663,
    "has_fixture": true,
    "has_cadquery_import": true,
    "error_kind": "build_ok"
  },
  {
    "reward_call": 35,
    "index": 2,
    "score": -0.565,
    "task_id": "bike_accessory_mount_120n",
    "code_chars": 5764,
    "cadforge_build": 0.0,
    "cadforge_total": -1.0,
    "has_fixture": true,
    "has_cadquery_import": true,
    "error_kind": "TypeError"
  },
  {
    "reward_call": 35,
    "index": 3,
    "score": -0.615,
    "task_id": "bike_accessory_mount_120n",
    "code_chars": 5731,
    "cadforge_build": 0.0,
    "cadforge_total": -1.0,
    "has_fixture": true,
    "has_cadquery_import": true,
    "error_kind": "NameError"
  },
  {
    "reward_call": 36,
    "index": 0,
    "score": -0.615,
    "task_id": "drawer_handle_two_bolt",
    "code_chars": 4283,
    "cadforge_build": 0.0,
    "cadforge_total": -1.0,
    "has_fixture": true,
    "has_cadquery_import": true,
    "error_kind": "NameError"
  },
  {
    "reward_call": 36,
    "index": 1,
    "score": 0.6973552631578949,
    "task_id": "drawer_handle_two_bolt",
    "code_chars": 2996,
    "cadforge_build": 1.0,
    "cadforge_total": 0.6439473684210527,
    "has_fixture": true,
    "has_cadquery_import": true,
    "error_kind": "build_ok"
  },
  {
    "reward_call": 36,
    "index": 2,
    "score": -0.84,
    "task_id": "ergonomic_curvy_chair_1000n",
    "code_chars": 4689,
    "cadforge_build": 0.0,
    "cadforge_total": -1.0,
    "has_fixture": false,
    "has_cadquery_import": true,
    "error_kind": "SyntaxError"
  },
  {
    "reward_call": 36,
    "index": 3,
    "score": -0.84,
    "task_id": "ergonomic_curvy_chair_1000n",
    "code_chars": 4988,
    "cadforge_build": 0.0,
    "cadforge_total": -1.0,
    "has_fixture": false,
    "has_cadquery_import": true,
    "error_kind": "SyntaxError"
  },
  {
    "reward_call": 37,
    "index": 0,
    "score": 0.7053947435579438,
    "task_id": "shelf_bracket_triangular_200n",
    "code_chars": 2517,
    "cadforge_build": 1.0,
    "cadforge_total": 0.6534055806564045,
    "has_fixture": true,
    "has_cadquery_import": true,
    "error_kind": "build_ok"
  },
  {
    "reward_call": 37,
    "index": 1,
    "score": 0.7518514895513351,
    "task_id": "shelf_bracket_triangular_200n",
    "code_chars": 3494,
    "cadforge_build": 1.0,
    "cadforge_total": 0.7080605759427472,
    "has_fixture": true,
    "has_cadquery_import": true,
    "error_kind": "build_ok"
  },
  {
    "reward_call": 37,
    "index": 2,
    "score": -0.6649999999999999,
    "task_id": "micro_drone_frame",
    "code_chars": 4736,
    "cadforge_build": 0.0,
    "cadforge_total": -1.0,
    "has_fixture": true,
    "has_cadquery_import": true,
    "error_kind": "SyntaxError"
  },
  {
    "reward_call": 37,
    "index": 3,
    "score": -0.565,
    "task_id": "micro_drone_frame",
    "code_chars": 5674,
    "cadforge_build": 0.0,
    "cadforge_total": -1.0,
    "has_fixture": true,
    "has_cadquery_import": true,
    "error_kind": "TypeError"
  },
  {
    "reward_call": 38,
    "index": 0,
    "score": -0.79,
    "task_id": "gearbox_housing_split",
    "code_chars": 6152,
    "cadforge_build": 0.0,
    "cadforge_total": -1.0,
    "has_fixture": false,
    "has_cadquery_import": true,
    "error_kind": "NameError"
  },
  {
    "reward_call": 38,
    "index": 1,
    "score": -0.84,
    "task_id": "gearbox_housing_split",
    "code_chars": 5504,
    "cadforge_build": 0.0,
    "cadforge_total": -1.0,
    "has_fixture": false,
    "has_cadquery_import": true,
    "error_kind": "SyntaxError"
  },
  {
    "reward_call": 38,
    "index": 2,
    "score": -0.79,
    "task_id": "cable_clip_snap",
    "code_chars": 5898,
    "cadforge_build": 0.0,
    "cadforge_total": -1.0,
    "has_fixture": false,
    "has_cadquery_import": true,
    "error_kind": "AttributeError"
  },
  {
    "reward_call": 38,
    "index": 3,
    "score": -0.6649999999999999,
    "task_id": "cable_clip_snap",
    "code_chars": 5345,
    "cadforge_build": 0.0,
    "cadforge_total": -1.0,
    "has_fixture": true,
    "has_cadquery_import": true,
    "error_kind": "SyntaxError"
  },
  {
    "reward_call": 39,
    "index": 0,
    "score": 0.6642500000000001,
    "task_id": "bottle_cage_bike",
    "code_chars": 4802,
    "cadforge_build": 1.0,
    "cadforge_total": 0.6050000000000001,
    "has_fixture": true,
    "has_cadquery_import": true,
    "error_kind": "build_ok"
  },
  {
    "reward_call": 39,
    "index": 1,
    "score": 0.8274949403962913,
    "task_id": "bottle_cage_bike",
    "code_chars": 4829,
    "cadforge_build": 1.0,
    "cadforge_total": 0.7970528710544604,
    "has_fixture": true,
    "has_cadquery_import": true,
    "error_kind": "build_ok"
  },
  {
    "reward_call": 39,
    "index": 2,
    "score": -0.74,
    "task_id": "folding_step_stool",
    "code_chars": 5732,
    "cadforge_build": 0.0,
    "cadforge_total": -1.0,
    "has_fixture": false,
    "has_cadquery_import": true,
    "error_kind": "ValueError"
  },
  {
    "reward_call": 39,
    "index": 3,
    "score": -0.84,
    "task_id": "folding_step_stool",
    "code_chars": 5252,
    "cadforge_build": 0.0,
    "cadforge_total": -1.0,
    "has_fixture": false,
    "has_cadquery_import": true,
    "error_kind": "SyntaxError"
  },
  {
    "reward_call": 40,
    "index": 0,
    "score": -0.565,
    "task_id": "hinge_leaf_barrel",
    "code_chars": 3500,
    "cadforge_build": 0.0,
    "cadforge_total": -1.0,
    "has_fixture": true,
    "has_cadquery_import": true,
    "error_kind": "TypeError"
  },
  {
    "reward_call": 40,
    "index": 1,
    "score": -0.695,
    "task_id": "hinge_leaf_barrel",
    "code_chars": 6200,
    "cadforge_build": 0.0,
    "cadforge_total": -1.0,
    "has_fixture": true,
    "has_cadquery_import": true,
    "error_kind": "SyntaxError"
  },
  {
    "reward_call": 40,
    "index": 2,
    "score": 0.7114237349456013,
    "task_id": "shaft_torque_clamp_120nm",
    "code_chars": 4587,
    "cadforge_build": 1.0,
    "cadforge_total": 0.6604985117007074,
    "has_fixture": true,
    "has_cadquery_import": true,
    "error_kind": "build_ok"
  },
  {
    "reward_call": 40,
    "index": 3,
    "score": 0.7068521044496177,
    "task_id": "shaft_torque_clamp_120nm",
    "code_chars": 3359,
    "cadforge_build": 1.0,
    "cadforge_total": 0.6551201228819031,
    "has_fixture": true,
    "has_cadquery_import": true,
    "error_kind": "build_ok"
  },
  {
    "reward_call": 41,
    "index": 0,
    "score": -0.565,
    "task_id": "cable_clip_snap",
    "code_chars": 3141,
    "cadforge_build": 0.0,
    "cadforge_total": -1.0,
    "has_fixture": true,
    "has_cadquery_import": true,
    "error_kind": "BRep_API"
  },
  {
    "reward_call": 41,
    "index": 1,
    "score": -0.565,
    "task_id": "cable_clip_snap",
    "code_chars": 3957,
    "cadforge_build": 0.0,
    "cadforge_total": -1.0,
    "has_fixture": true,
    "has_cadquery_import": true,
    "error_kind": "unknown"
  },
  {
    "reward_call": 41,
    "index": 2,
    "score": 0.871946352186128,
    "task_id": "pipe_clamp_saddle",
    "code_chars": 2954,
    "cadforge_build": 1.0,
    "cadforge_total": 0.8493486496307389,
    "has_fixture": true,
    "has_cadquery_import": true,
    "error_kind": "build_ok"
  },
  {
    "reward_call": 41,
    "index": 3,
    "score": -0.6649999999999999,
    "task_id": "pipe_clamp_saddle",
    "code_chars": 2681,
    "cadforge_build": 0.0,
    "cadforge_total": -1.0,
    "has_fixture": true,
    "has_cadquery_import": true,
    "error_kind": "SyntaxError"
  },
  {
    "reward_call": 42,
    "index": 0,
    "score": -0.615,
    "task_id": "laptop_riser_vented",
    "code_chars": 4234,
    "cadforge_build": 0.0,
    "cadforge_total": -1.0,
    "has_fixture": true,
    "has_cadquery_import": true,
    "error_kind": "NameError"
  },
  {
    "reward_call": 42,
    "index": 1,
    "score": -0.6649999999999999,
    "task_id": "laptop_riser_vented",
    "code_chars": 3876,
    "cadforge_build": 0.0,
    "cadforge_total": -1.0,
    "has_fixture": true,
    "has_cadquery_import": true,
    "error_kind": "SyntaxError"
  },
  {
    "reward_call": 42,
    "index": 2,
    "score": -0.615,
    "task_id": "hinge_leaf_barrel",
    "code_chars": 4904,
    "cadforge_build": 0.0,
    "cadforge_total": -1.0,
    "has_fixture": true,
    "has_cadquery_import": true,
    "error_kind": "AttributeError"
  },
  {
    "reward_call": 42,
    "index": 3,
    "score": -0.565,
    "task_id": "hinge_leaf_barrel",
    "code_chars": 4744,
    "cadforge_build": 0.0,
    "cadforge_total": -1.0,
    "has_fixture": true,
    "has_cadquery_import": true,
    "error_kind": "ValueError"
  },
  {
    "reward_call": 43,
    "index": 0,
    "score": -0.6649999999999999,
    "task_id": "bottle_cage_bike",
    "code_chars": 6217,
    "cadforge_build": 0.0,
    "cadforge_total": -1.0,
    "has_fixture": true,
    "has_cadquery_import": true,
    "error_kind": "SyntaxError"
  },
  {
    "reward_call": 43,
    "index": 1,
    "score": -0.565,
    "task_id": "bottle_cage_bike",
    "code_chars": 4560,
    "cadforge_build": 0.0,
    "cadforge_total": -1.0,
    "has_fixture": true,
    "has_cadquery_import": true,
    "error_kind": "ValueError"
  },
  {
    "reward_call": 43,
    "index": 2,
    "score": -0.84,
    "task_id": "ergonomic_curvy_chair_1000n",
    "code_chars": 5147,
    "cadforge_build": 0.0,
    "cadforge_total": -1.0,
    "has_fixture": false,
    "has_cadquery_import": true,
    "error_kind": "SyntaxError"
  },
  {
    "reward_call": 43,
    "index": 3,
    "score": -0.84,
    "task_id": "ergonomic_curvy_chair_1000n",
    "code_chars": 4709,
    "cadforge_build": 0.0,
    "cadforge_total": -1.0,
    "has_fixture": false,
    "has_cadquery_import": true,
    "error_kind": "SyntaxError"
  },
  {
    "reward_call": 44,
    "index": 0,
    "score": -0.615,
    "task_id": "micro_drone_frame",
    "code_chars": 4444,
    "cadforge_build": 0.0,
    "cadforge_total": -1.0,
    "has_fixture": true,
    "has_cadquery_import": true,
    "error_kind": "AttributeError"
  },
  {
    "reward_call": 44,
    "index": 1,
    "score": -0.79,
    "task_id": "micro_drone_frame",
    "code_chars": 5540,
    "cadforge_build": 0.0,
    "cadforge_total": -1.0,
    "has_fixture": false,
    "has_cadquery_import": true,
    "error_kind": "NameError"
  },
  {
    "reward_call": 44,
    "index": 2,
    "score": -0.6649999999999999,
    "task_id": "table_six_leg_500n",
    "code_chars": 4577,
    "cadforge_build": 0.0,
    "cadforge_total": -1.0,
    "has_fixture": true,
    "has_cadquery_import": true,
    "error_kind": "SyntaxError"
  },
  {
    "reward_call": 44,
    "index": 3,
    "score": 0.8346430625994663,
    "task_id": "table_six_leg_500n",
    "code_chars": 3110,
    "cadforge_build": 1.0,
    "cadforge_total": 0.8054624265876075,
    "has_fixture": true,
    "has_cadquery_import": true,
    "error_kind": "build_ok"
  },
  {
    "reward_call": 45,
    "index": 0,
    "score": -0.84,
    "task_id": "folding_step_stool",
    "code_chars": 4872,
    "cadforge_build": 0.0,
    "cadforge_total": -1.0,
    "has_fixture": false,
    "has_cadquery_import": true,
    "error_kind": "SyntaxError"
  },
  {
    "reward_call": 45,
    "index": 1,
    "score": -0.79,
    "task_id": "folding_step_stool",
    "code_chars": 5138,
    "cadforge_build": 0.0,
    "cadforge_total": -1.0,
    "has_fixture": false,
    "has_cadquery_import": true,
    "error_kind": "AttributeError"
  },
  {
    "reward_call": 45,
    "index": 2,
    "score": 0.7470980837605303,
    "task_id": "desk_lamp_arm_joint",
    "code_chars": 5844,
    "cadforge_build": 1.0,
    "cadforge_total": 0.702468333835918,
    "has_fixture": true,
    "has_cadquery_import": true,
    "error_kind": "build_ok"
  },
  {
    "reward_call": 45,
    "index": 3,
    "score": 0.6401666666666668,
    "task_id": "desk_lamp_arm_joint",
    "code_chars": 4613,
    "cadforge_build": 1.0,
    "cadforge_total": 0.5766666666666668,
    "has_fixture": true,
    "has_cadquery_import": true,
    "error_kind": "build_ok"
  },
  {
    "reward_call": 46,
    "index": 0,
    "score": -0.61,
    "task_id": "wall_j_hook_120n",
    "code_chars": 3407,
    "cadforge_build": 0.0,
    "cadforge_total": -1.0,
    "has_fixture": true,
    "has_cadquery_import": true,
    "error_kind": "TypeError"
  },
  {
    "reward_call": 46,
    "index": 1,
    "score": -0.565,
    "task_id": "wall_j_hook_120n",
    "code_chars": 3003,
    "cadforge_build": 0.0,
    "cadforge_total": -1.0,
    "has_fixture": true,
    "has_cadquery_import": true,
    "error_kind": "ValueError"
  },
  {
    "reward_call": 46,
    "index": 2,
    "score": 0.8369582933584849,
    "task_id": "lightweight_truss_support_250n",
    "code_chars": 4804,
    "cadforge_build": 1.0,
    "cadforge_total": 0.8081862274805705,
    "has_fixture": true,
    "has_cadquery_import": true,
    "error_kind": "build_ok"
  },
  {
    "reward_call": 46,
    "index": 3,
    "score": -0.84,
    "task_id": "lightweight_truss_support_250n",
    "code_chars": 4454,
    "cadforge_build": 0.0,
    "cadforge_total": -1.0,
    "has_fixture": false,
    "has_cadquery_import": true,
    "error_kind": "SyntaxError"
  },
  {
    "reward_call": 47,
    "index": 0,
    "score": -0.615,
    "task_id": "robot_gripper_two_finger",
    "code_chars": 5250,
    "cadforge_build": 0.0,
    "cadforge_total": -1.0,
    "has_fixture": true,
    "has_cadquery_import": true,
    "error_kind": "AttributeError"
  },
  {
    "reward_call": 47,
    "index": 1,
    "score": 0.6997138900547093,
    "task_id": "robot_gripper_two_finger",
    "code_chars": 3424,
    "cadforge_build": 1.0,
    "cadforge_total": 0.6467222235937756,
    "has_fixture": true,
    "has_cadquery_import": true,
    "error_kind": "build_ok"
  },
  {
    "reward_call": 47,
    "index": 2,
    "score": -0.84,
    "task_id": "gearbox_housing_split",
    "code_chars": 6428,
    "cadforge_build": 0.0,
    "cadforge_total": -1.0,
    "has_fixture": false,
    "has_cadquery_import": true,
    "error_kind": "SyntaxError"
  },
  {
    "reward_call": 47,
    "index": 3,
    "score": -0.84,
    "task_id": "gearbox_housing_split",
    "code_chars": 5680,
    "cadforge_build": 0.0,
    "cadforge_total": -1.0,
    "has_fixture": false,
    "has_cadquery_import": true,
    "error_kind": "SyntaxError"
  },
  {
    "reward_call": 48,
    "index": 0,
    "score": 0.6672099629296073,
    "task_id": "drawer_handle_two_bolt",
    "code_chars": 3586,
    "cadforge_build": 1.0,
    "cadforge_total": 0.6084823093289498,
    "has_fixture": true,
    "has_cadquery_import": true,
    "error_kind": "build_ok"
  },
  {
    "reward_call": 48,
    "index": 1,
    "score": 0.6671490277904167,
    "task_id": "drawer_handle_two_bolt",
    "code_chars": 2160,
    "cadforge_build": 1.0,
    "cadforge_total": 0.6084106209299021,
    "has_fixture": true,
    "has_cadquery_import": true,
    "error_kind": "build_ok"
  },
  {
    "reward_call": 48,
    "index": 2,
    "score": 0.7806319796949592,
    "task_id": "shelf_bracket_triangular_200n",
    "code_chars": 2611,
    "cadforge_build": 1.0,
    "cadforge_total": 0.7419199761117168,
    "has_fixture": true,
    "has_cadquery_import": true,
    "error_kind": "build_ok"
  },
  {
    "reward_call": 48,
    "index": 3,
    "score": -0.615,
    "task_id": "shelf_bracket_triangular_200n",
    "code_chars": 2611,
    "cadforge_build": 0.0,
    "cadforge_total": -1.0,
    "has_fixture": true,
    "has_cadquery_import": true,
    "error_kind": "NameError"
  },
  {
    "reward_call": 49,
    "index": 0,
    "score": -0.6649999999999999,
    "task_id": "bike_accessory_mount_120n",
    "code_chars": 2505,
    "cadforge_build": 0.0,
    "cadforge_total": -1.0,
    "has_fixture": true,
    "has_cadquery_import": true,
    "error_kind": "SyntaxError"
  },
  {
    "reward_call": 49,
    "index": 1,
    "score": 0.7575464783499094,
    "task_id": "bike_accessory_mount_120n",
    "code_chars": 3589,
    "cadforge_build": 1.0,
    "cadforge_total": 0.7147605627645993,
    "has_fixture": true,
    "has_cadquery_import": true,
    "error_kind": "build_ok"
  },
  {
    "reward_call": 49,
    "index": 2,
    "score": -0.565,
    "task_id": "shaft_torque_clamp_120nm",
    "code_chars": 4131,
    "cadforge_build": 0.0,
    "cadforge_total": -1.0,
    "has_fixture": true,
    "has_cadquery_import": true,
    "error_kind": "ValueError"
  },
  {
    "reward_call": 49,
    "index": 3,
    "score": -0.565,
    "task_id": "shaft_torque_clamp_120nm",
    "code_chars": 5495,
    "cadforge_build": 0.0,
    "cadforge_total": -1.0,
    "has_fixture": true,
    "has_cadquery_import": true,
    "error_kind": "unknown"
  },
  {
    "reward_call": 50,
    "index": 0,
    "score": -0.84,
    "task_id": "bench_vise_simplified",
    "code_chars": 5814,
    "cadforge_build": 0.0,
    "cadforge_total": -1.0,
    "has_fixture": false,
    "has_cadquery_import": true,
    "error_kind": "SyntaxError"
  },
  {
    "reward_call": 50,
    "index": 1,
    "score": -0.6649999999999999,
    "task_id": "bench_vise_simplified",
    "code_chars": 4253,
    "cadforge_build": 0.0,
    "cadforge_total": -1.0,
    "has_fixture": true,
    "has_cadquery_import": true,
    "error_kind": "SyntaxError"
  },
  {
    "reward_call": 50,
    "index": 2,
    "score": -0.565,
    "task_id": "phone_stand_adjustable_hinge",
    "code_chars": 4290,
    "cadforge_build": 0.0,
    "cadforge_total": -1.0,
    "has_fixture": true,
    "has_cadquery_import": true,
    "error_kind": "unknown"
  },
  {
    "reward_call": 50,
    "index": 3,
    "score": 0.8716593817974053,
    "task_id": "phone_stand_adjustable_hinge",
    "code_chars": 5004,
    "cadforge_build": 1.0,
    "cadforge_total": 0.8490110374087122,
    "has_fixture": true,
    "has_cadquery_import": true,
    "error_kind": "build_ok"
  },
  {
    "reward_call": 51,
    "index": 0,
    "score": -0.645,
    "task_id": "drawer_handle_two_bolt",
    "code_chars": 3333,
    "cadforge_build": 0.0,
    "cadforge_total": -1.0,
    "has_fixture": true,
    "has_cadquery_import": true,
    "error_kind": "NameError"
  },
  {
    "reward_call": 51,
    "index": 1,
    "score": -0.565,
    "task_id": "drawer_handle_two_bolt",
    "code_chars": 4063,
    "cadforge_build": 0.0,
    "cadforge_total": -1.0,
    "has_fixture": true,
    "has_cadquery_import": true,
    "error_kind": "BRep_API"
  },
  {
    "reward_call": 51,
    "index": 2,
    "score": -0.615,
    "task_id": "shelf_bracket_triangular_200n",
    "code_chars": 3539,
    "cadforge_build": 0.0,
    "cadforge_total": -1.0,
    "has_fixture": true,
    "has_cadquery_import": true,
    "error_kind": "NameError"
  },
  {
    "reward_call": 51,
    "index": 3,
    "score": 0.7474324364269804,
    "task_id": "shelf_bracket_triangular_200n",
    "code_chars": 3226,
    "cadforge_build": 1.0,
    "cadforge_total": 0.7028616899140946,
    "has_fixture": true,
    "has_cadquery_import": true,
    "error_kind": "build_ok"
  },
  {
    "reward_call": 52,
    "index": 0,
    "score": -0.565,
    "task_id": "hinge_leaf_barrel",
    "code_chars": 4252,
    "cadforge_build": 0.0,
    "cadforge_total": -1.0,
    "has_fixture": true,
    "has_cadquery_import": true,
    "error_kind": "unknown"
  },
  {
    "reward_call": 52,
    "index": 1,
    "score": -0.595,
    "task_id": "hinge_leaf_barrel",
    "code_chars": 4008,
    "cadforge_build": 0.0,
    "cadforge_total": -1.0,
    "has_fixture": true,
    "has_cadquery_import": true,
    "error_kind": "ValueError"
  },
  {
    "reward_call": 52,
    "index": 2,
    "score": -0.565,
    "task_id": "desk_lamp_arm_joint",
    "code_chars": 5156,
    "cadforge_build": 0.0,
    "cadforge_total": -1.0,
    "has_fixture": true,
    "has_cadquery_import": true,
    "error_kind": "TypeError"
  },
  {
    "reward_call": 52,
    "index": 3,
    "score": -0.79,
    "task_id": "desk_lamp_arm_joint",
    "code_chars": 6164,
    "cadforge_build": 0.0,
    "cadforge_total": -1.0,
    "has_fixture": true,
    "has_cadquery_import": true,
    "error_kind": "NameError"
  },
  {
    "reward_call": 53,
    "index": 0,
    "score": 0.8105635620789096,
    "task_id": "shaft_torque_clamp_120nm",
    "code_chars": 3731,
    "cadforge_build": 1.0,
    "cadforge_total": 0.7771336024457759,
    "has_fixture": true,
    "has_cadquery_import": true,
    "error_kind": "build_ok"
  },
  {
    "reward_call": 53,
    "index": 1,
    "score": 0.7106959361884481,
    "task_id": "shaft_torque_clamp_120nm",
    "code_chars": 4878,
    "cadforge_build": 1.0,
    "cadforge_total": 0.6596422778687624,
    "has_fixture": true,
    "has_cadquery_import": true,
    "error_kind": "build_ok"
  },
  {
    "reward_call": 53,
    "index": 2,
    "score": 0.6823218111628114,
    "task_id": "robot_gripper_two_finger",
    "code_chars": 5130,
    "cadforge_build": 1.0,
    "cadforge_total": 0.6262609543091899,
    "has_fixture": true,
    "has_cadquery_import": true,
    "error_kind": "build_ok"
  },
  {
    "reward_call": 53,
    "index": 3,
    "score": -0.645,
    "task_id": "robot_gripper_two_finger",
    "code_chars": 4339,
    "cadforge_build": 0.0,
    "cadforge_total": -1.0,
    "has_fixture": true,
    "has_cadquery_import": true,
    "error_kind": "NameError"
  },
  {
    "reward_call": 54,
    "index": 0,
    "score": -0.84,
    "task_id": "folding_step_stool",
    "code_chars": 5807,
    "cadforge_build": 0.0,
    "cadforge_total": -1.0,
    "has_fixture": false,
    "has_cadquery_import": true,
    "error_kind": "SyntaxError"
  },
  {
    "reward_call": 54,
    "index": 1,
    "score": -0.84,
    "task_id": "folding_step_stool",
    "code_chars": 6139,
    "cadforge_build": 0.0,
    "cadforge_total": -1.0,
    "has_fixture": false,
    "has_cadquery_import": true,
    "error_kind": "SyntaxError"
  },
  {
    "reward_call": 54,
    "index": 2,
    "score": 0.7464098823051949,
    "task_id": "pipe_clamp_saddle",
    "code_chars": 5033,
    "cadforge_build": 1.0,
    "cadforge_total": 0.7016586850649351,
    "has_fixture": true,
    "has_cadquery_import": true,
    "error_kind": "build_ok"
  },
  {
    "reward_call": 54,
    "index": 3,
    "score": -0.565,
    "task_id": "pipe_clamp_saddle",
    "code_chars": 4372,
    "cadforge_build": 0.0,
    "cadforge_total": -1.0,
    "has_fixture": true,
    "has_cadquery_import": true,
    "error_kind": "TypeError"
  },
  {
    "reward_call": 55,
    "index": 0,
    "score": 0.6493090788741098,
    "task_id": "wall_j_hook_120n",
    "code_chars": 3841,
    "cadforge_build": 1.0,
    "cadforge_total": 0.5874224457342468,
    "has_fixture": true,
    "has_cadquery_import": true,
    "error_kind": "build_ok"
  },
  {
    "reward_call": 55,
    "index": 1,
    "score": -0.565,
    "task_id": "wall_j_hook_120n",
    "code_chars": 3368,
    "cadforge_build": 0.0,
    "cadforge_total": -1.0,
    "has_fixture": true,
    "has_cadquery_import": true,
    "error_kind": "ValueError"
  },
  {
    "reward_call": 55,
    "index": 2,
    "score": -0.84,
    "task_id": "gearbox_housing_split",
    "code_chars": 5987,
    "cadforge_build": 0.0,
    "cadforge_total": -1.0,
    "has_fixture": false,
    "has_cadquery_import": true,
    "error_kind": "SyntaxError"
  },
  {
    "reward_call": 55,
    "index": 3,
    "score": -0.8699999999999999,
    "task_id": "gearbox_housing_split",
    "code_chars": 5467,
    "cadforge_build": 0.0,
    "cadforge_total": -1.0,
    "has_fixture": false,
    "has_cadquery_import": true,
    "error_kind": "SyntaxError"
  },
  {
    "reward_call": 56,
    "index": 0,
    "score": -0.84,
    "task_id": "lightweight_truss_support_250n",
    "code_chars": 4523,
    "cadforge_build": 0.0,
    "cadforge_total": -1.0,
    "has_fixture": false,
    "has_cadquery_import": true,
    "error_kind": "SyntaxError"
  },
  {
    "reward_call": 56,
    "index": 1,
    "score": -0.645,
    "task_id": "lightweight_truss_support_250n",
    "code_chars": 4927,
    "cadforge_build": 0.0,
    "cadforge_total": -1.0,
    "has_fixture": true,
    "has_cadquery_import": true,
    "error_kind": "AttributeError"
  },
  {
    "reward_call": 56,
    "index": 2,
    "score": 0.7611631331328613,
    "task_id": "laptop_riser_vented",
    "code_chars": 3601,
    "cadforge_build": 1.0,
    "cadforge_total": 0.7190154507445428,
    "has_fixture": true,
    "has_cadquery_import": true,
    "error_kind": "build_ok"
  },
  {
    "reward_call": 56,
    "index": 3,
    "score": 0.7619837729036159,
    "task_id": "laptop_riser_vented",
    "code_chars": 3894,
    "cadforge_build": 1.0,
    "cadforge_total": 0.7199809092983716,
    "has_fixture": true,
    "has_cadquery_import": true,
    "error_kind": "build_ok"
  },
  {
    "reward_call": 57,
    "index": 0,
    "score": -0.8849999999999999,
    "task_id": "bench_vise_simplified",
    "code_chars": 5492,
    "cadforge_build": 0.0,
    "cadforge_total": -1.0,
    "has_fixture": false,
    "has_cadquery_import": true,
    "error_kind": "SyntaxError"
  },
  {
    "reward_call": 57,
    "index": 1,
    "score": -0.7849999999999999,
    "task_id": "bench_vise_simplified",
    "code_chars": 5359,
    "cadforge_build": 0.0,
    "cadforge_total": -1.0,
    "has_fixture": false,
    "has_cadquery_import": true,
    "error_kind": "ValueError"
  },
  {
    "reward_call": 57,
    "index": 2,
    "score": 0.7362512650469238,
    "task_id": "micro_drone_frame",
    "code_chars": 5453,
    "cadforge_build": 1.0,
    "cadforge_total": 0.6897073706434398,
    "has_fixture": true,
    "has_cadquery_import": true,
    "error_kind": "build_ok"
  },
  {
    "reward_call": 57,
    "index": 3,
    "score": -0.84,
    "task_id": "micro_drone_frame",
    "code_chars": 5941,
    "cadforge_build": 0.0,
    "cadforge_total": -1.0,
    "has_fixture": false,
    "has_cadquery_import": true,
    "error_kind": "SyntaxError"
  },
  {
    "reward_call": 58,
    "index": 0,
    "score": -0.84,
    "task_id": "ergonomic_curvy_chair_1000n",
    "code_chars": 4919,
    "cadforge_build": 0.0,
    "cadforge_total": -1.0,
    "has_fixture": false,
    "has_cadquery_import": true,
    "error_kind": "SyntaxError"
  },
  {
    "reward_call": 58,
    "index": 1,
    "score": -0.74,
    "task_id": "ergonomic_curvy_chair_1000n",
    "code_chars": 5406,
    "cadforge_build": 0.0,
    "cadforge_total": -1.0,
    "has_fixture": false,
    "has_cadquery_import": true,
    "error_kind": "ValueError"
  },
  {
    "reward_call": 58,
    "index": 2,
    "score": 0.889293602353931,
    "task_id": "phone_stand_adjustable_hinge",
    "code_chars": 4588,
    "cadforge_build": 1.0,
    "cadforge_total": 0.8697571792399188,
    "has_fixture": true,
    "has_cadquery_import": true,
    "error_kind": "build_ok"
  },
  {
    "reward_call": 58,
    "index": 3,
    "score": 0.7180833333333333,
    "task_id": "phone_stand_adjustable_hinge",
    "code_chars": 3710,
    "cadforge_build": 1.0,
    "cadforge_total": 0.6683333333333333,
    "has_fixture": true,
    "has_cadquery_import": true,
    "error_kind": "build_ok"
  },
  {
    "reward_call": 59,
    "index": 0,
    "score": -0.6649999999999999,
    "task_id": "table_six_leg_500n",
    "code_chars": 3985,
    "cadforge_build": 0.0,
    "cadforge_total": -1.0,
    "has_fixture": true,
    "has_cadquery_import": true,
    "error_kind": "SyntaxError"
  },
  {
    "reward_call": 59,
    "index": 1,
    "score": 0.7751041666666667,
    "task_id": "table_six_leg_500n",
    "code_chars": 4474,
    "cadforge_build": 1.0,
    "cadforge_total": 0.7354166666666667,
    "has_fixture": true,
    "has_cadquery_import": true,
    "error_kind": "build_ok"
  },
  {
    "reward_call": 59,
    "index": 2,
    "score": -0.565,
    "task_id": "bike_accessory_mount_120n",
    "code_chars": 3449,
    "cadforge_build": 0.0,
    "cadforge_total": -1.0,
    "has_fixture": true,
    "has_cadquery_import": true,
    "error_kind": "unknown"
  },
  {
    "reward_call": 59,
    "index": 3,
    "score": -0.6649999999999999,
    "task_id": "bike_accessory_mount_120n",
    "code_chars": 5347,
    "cadforge_build": 0.0,
    "cadforge_total": -1.0,
    "has_fixture": true,
    "has_cadquery_import": true,
    "error_kind": "SyntaxError"
  },
  {
    "reward_call": 60,
    "index": 0,
    "score": 0.7578764590434719,
    "task_id": "bottle_cage_bike",
    "code_chars": 3193,
    "cadforge_build": 1.0,
    "cadforge_total": 0.715148775345261,
    "has_fixture": true,
    "has_cadquery_import": true,
    "error_kind": "build_ok"
  },
  {
    "reward_call": 60,
    "index": 1,
    "score": -0.615,
    "task_id": "bottle_cage_bike",
    "code_chars": 4094,
    "cadforge_build": 0.0,
    "cadforge_total": -1.0,
    "has_fixture": true,
    "has_cadquery_import": true,
    "error_kind": "AttributeError"
  },
  {
    "reward_call": 60,
    "index": 2,
    "score": -0.6649999999999999,
    "task_id": "cable_clip_snap",
    "code_chars": 5720,
    "cadforge_build": 0.0,
    "cadforge_total": -1.0,
    "has_fixture": true,
    "has_cadquery_import": true,
    "error_kind": "SyntaxError"
  },
  {
    "reward_call": 60,
    "index": 3,
    "score": 0.7115461458630677,
    "task_id": "cable_clip_snap",
    "code_chars": 4541,
    "cadforge_build": 1.0,
    "cadforge_total": 0.6606425245447856,
    "has_fixture": true,
    "has_cadquery_import": true,
    "error_kind": "build_ok"
  },
  {
    "reward_call": 61,
    "index": 0,
    "score": -0.61,
    "task_id": "laptop_riser_vented",
    "code_chars": 5017,
    "cadforge_build": 0.0,
    "cadforge_total": -1.0,
    "has_fixture": true,
    "has_cadquery_import": true,
    "error_kind": "TypeError"
  },
  {
    "reward_call": 61,
    "index": 1,
    "score": 0.8574772795845026,
    "task_id": "laptop_riser_vented",
    "code_chars": 4781,
    "cadforge_build": 1.0,
    "cadforge_total": 0.8323262112758855,
    "has_fixture": true,
    "has_cadquery_import": true,
    "error_kind": "build_ok"
  },
  {
    "reward_call": 61,
    "index": 2,
    "score": -0.615,
    "task_id": "wall_j_hook_120n",
    "code_chars": 4160,
    "cadforge_build": 0.0,
    "cadforge_total": -1.0,
    "has_fixture": true,
    "has_cadquery_import": true,
    "error_kind": "NameError"
  },
  {
    "reward_call": 61,
    "index": 3,
    "score": -0.615,
    "task_id": "wall_j_hook_120n",
    "code_chars": 2626,
    "cadforge_build": 0.0,
    "cadforge_total": -1.0,
    "has_fixture": true,
    "has_cadquery_import": true,
    "error_kind": "AttributeError"
  },
  {
    "reward_call": 62,
    "index": 0,
    "score": -0.565,
    "task_id": "desk_lamp_arm_joint",
    "code_chars": 5457,
    "cadforge_build": 0.0,
    "cadforge_total": -1.0,
    "has_fixture": true,
    "has_cadquery_import": true,
    "error_kind": "TypeError"
  },
  {
    "reward_call": 62,
    "index": 1,
    "score": -0.84,
    "task_id": "desk_lamp_arm_joint",
    "code_chars": 5326,
    "cadforge_build": 0.0,
    "cadforge_total": -1.0,
    "has_fixture": false,
    "has_cadquery_import": true,
    "error_kind": "SyntaxError"
  },
  {
    "reward_call": 62,
    "index": 2,
    "score": -0.6649999999999999,
    "task_id": "cable_clip_snap",
    "code_chars": 5669,
    "cadforge_build": 0.0,
    "cadforge_total": -1.0,
    "has_fixture": true,
    "has_cadquery_import": true,
    "error_kind": "SyntaxError"
  },
  {
    "reward_call": 62,
    "index": 3,
    "score": -0.66,
    "task_id": "cable_clip_snap",
    "code_chars": 4840,
    "cadforge_build": 0.0,
    "cadforge_total": -1.0,
    "has_fixture": true,
    "has_cadquery_import": true,
    "error_kind": "NameError"
  },
  {
    "reward_call": 63,
    "index": 0,
    "score": -0.6649999999999999,
    "task_id": "lightweight_truss_support_250n",
    "code_chars": 5609,
    "cadforge_build": 0.0,
    "cadforge_total": -1.0,
    "has_fixture": true,
    "has_cadquery_import": true,
    "error_kind": "SyntaxError"
  },
  {
    "reward_call": 63,
    "index": 1,
    "score": 0.7126822916666666,
    "task_id": "lightweight_truss_support_250n",
    "code_chars": 3365,
    "cadforge_build": 1.0,
    "cadforge_total": 0.6619791666666667,
    "has_fixture": true,
    "has_cadquery_import": true,
    "error_kind": "build_ok"
  },
  {
    "reward_call": 63,
    "index": 2,
    "score": -0.84,
    "task_id": "gearbox_housing_split",
    "code_chars": 6067,
    "cadforge_build": 0.0,
    "cadforge_total": -1.0,
    "has_fixture": false,
    "has_cadquery_import": true,
    "error_kind": "SyntaxError"
  },
  {
    "reward_call": 63,
    "index": 3,
    "score": -0.84,
    "task_id": "gearbox_housing_split",
    "code_chars": 5620,
    "cadforge_build": 0.0,
    "cadforge_total": -1.0,
    "has_fixture": false,
    "has_cadquery_import": true,
    "error_kind": "SyntaxError"
  },
  {
    "reward_call": 64,
    "index": 0,
    "score": -0.615,
    "task_id": "bottle_cage_bike",
    "code_chars": 4779,
    "cadforge_build": 0.0,
    "cadforge_total": -1.0,
    "has_fixture": true,
    "has_cadquery_import": true,
    "error_kind": "NameError"
  },
  {
    "reward_call": 64,
    "index": 1,
    "score": -0.615,
    "task_id": "bottle_cage_bike",
    "code_chars": 6025,
    "cadforge_build": 0.0,
    "cadforge_total": -1.0,
    "has_fixture": true,
    "has_cadquery_import": true,
    "error_kind": "NameError"
  },
  {
    "reward_call": 64,
    "index": 2,
    "score": -0.74,
    "task_id": "micro_drone_frame",
    "code_chars": 5747,
    "cadforge_build": 0.0,
    "cadforge_total": -1.0,
    "has_fixture": false,
    "has_cadquery_import": true,
    "error_kind": "ValueError"
  },
  {
    "reward_call": 64,
    "index": 3,
    "score": -0.615,
    "task_id": "micro_drone_frame",
    "code_chars": 5582,
    "cadforge_build": 0.0,
    "cadforge_total": -1.0,
    "has_fixture": true,
    "has_cadquery_import": true,
    "error_kind": "AttributeError"
  },
  {
    "reward_call": 65,
    "index": 0,
    "score": -0.74,
    "task_id": "phone_stand_adjustable_hinge",
    "code_chars": 5572,
    "cadforge_build": 0.0,
    "cadforge_total": -1.0,
    "has_fixture": false,
    "has_cadquery_import": true,
    "error_kind": "ValueError"
  },
  {
    "reward_call": 65,
    "index": 1,
    "score": 0.9449412121370865,
    "task_id": "phone_stand_adjustable_hinge",
    "code_chars": 3965,
    "cadforge_build": 1.0,
    "cadforge_total": 0.9352249554553959,
    "has_fixture": true,
    "has_cadquery_import": true,
    "error_kind": "build_ok"
  },
  {
    "reward_call": 65,
    "index": 2,
    "score": -0.61,
    "task_id": "robot_gripper_two_finger",
    "code_chars": 4726,
    "cadforge_build": 0.0,
    "cadforge_total": -1.0,
    "has_fixture": true,
    "has_cadquery_import": true,
    "error_kind": "unknown"
  },
  {
    "reward_call": 65,
    "index": 3,
    "score": 0.72758080696295,
    "task_id": "robot_gripper_two_finger",
    "code_chars": 3254,
    "cadforge_build": 1.0,
    "cadforge_total": 0.6795068317211177,
    "has_fixture": true,
    "has_cadquery_import": true,
    "error_kind": "build_ok"
  },
  {
    "reward_call": 66,
    "index": 0,
    "score": 0.6171452781088472,
    "task_id": "bench_vise_simplified",
    "code_chars": 5564,
    "cadforge_build": 1.0,
    "cadforge_total": 0.5495826801280556,
    "has_fixture": true,
    "has_cadquery_import": true,
    "error_kind": "build_ok"
  },
  {
    "reward_call": 66,
    "index": 1,
    "score": -0.84,
    "task_id": "bench_vise_simplified",
    "code_chars": 5617,
    "cadforge_build": 0.0,
    "cadforge_total": -1.0,
    "has_fixture": false,
    "has_cadquery_import": true,
    "error_kind": "SyntaxError"
  },
  {
    "reward_call": 66,
    "index": 2,
    "score": 0.7287083333333334,
    "task_id": "pipe_clamp_saddle",
    "code_chars": 4561,
    "cadforge_build": 1.0,
    "cadforge_total": 0.6808333333333334,
    "has_fixture": true,
    "has_cadquery_import": true,
    "error_kind": "build_ok"
  },
  {
    "reward_call": 66,
    "index": 3,
    "score": -0.6900000000000001,
    "task_id": "pipe_clamp_saddle",
    "code_chars": 3756,
    "cadforge_build": 0.0,
    "cadforge_total": -1.0,
    "has_fixture": true,
    "has_cadquery_import": true,
    "error_kind": "NameError"
  },
  {
    "reward_call": 67,
    "index": 0,
    "score": -0.595,
    "task_id": "drawer_handle_two_bolt",
    "code_chars": 3019,
    "cadforge_build": 0.0,
    "cadforge_total": -1.0,
    "has_fixture": true,
    "has_cadquery_import": true,
    "error_kind": "unknown"
  },
  {
    "reward_call": 67,
    "index": 1,
    "score": 0.7683493216086832,
    "task_id": "drawer_handle_two_bolt",
    "code_chars": 2128,
    "cadforge_build": 1.0,
    "cadforge_total": 0.7274697901278626,
    "has_fixture": true,
    "has_cadquery_import": true,
    "error_kind": "build_ok"
  },
  {
    "reward_call": 67,
    "index": 2,
    "score": -0.565,
    "task_id": "hinge_leaf_barrel",
    "code_chars": 4949,
    "cadforge_build": 0.0,
    "cadforge_total": -1.0,
    "has_fixture": true,
    "has_cadquery_import": true,
    "error_kind": "unknown"
  },
  {
    "reward_call": 67,
    "index": 3,
    "score": -0.595,
    "task_id": "hinge_leaf_barrel",
    "code_chars": 5208,
    "cadforge_build": 0.0,
    "cadforge_total": -1.0,
    "has_fixture": true,
    "has_cadquery_import": true,
    "error_kind": "TypeError"
  },
  {
    "reward_call": 68,
    "index": 0,
    "score": 0.7240374070978418,
    "task_id": "shelf_bracket_triangular_200n",
    "code_chars": 2343,
    "cadforge_build": 1.0,
    "cadforge_total": 0.6753381259974609,
    "has_fixture": true,
    "has_cadquery_import": true,
    "error_kind": "build_ok"
  },
  {
    "reward_call": 68,
    "index": 1,
    "score": 0.81054143511043,
    "task_id": "shelf_bracket_triangular_200n",
    "code_chars": 3230,
    "cadforge_build": 1.0,
    "cadforge_total": 0.777107570718153,
    "has_fixture": true,
    "has_cadquery_import": true,
    "error_kind": "build_ok"
  },
  {
    "reward_call": 68,
    "index": 2,
    "score": -0.6649999999999999,
    "task_id": "shaft_torque_clamp_120nm",
    "code_chars": 5108,
    "cadforge_build": 0.0,
    "cadforge_total": -1.0,
    "has_fixture": true,
    "has_cadquery_import": true,
    "error_kind": "SyntaxError"
  },
  {
    "reward_call": 68,
    "index": 3,
    "score": -0.565,
    "task_id": "shaft_torque_clamp_120nm",
    "code_chars": 4955,
    "cadforge_build": 0.0,
    "cadforge_total": -1.0,
    "has_fixture": true,
    "has_cadquery_import": true,
    "error_kind": "unknown"
  },
  {
    "reward_call": 69,
    "index": 0,
    "score": -0.565,
    "task_id": "bike_accessory_mount_120n",
    "code_chars": 4445,
    "cadforge_build": 0.0,
    "cadforge_total": -1.0,
    "has_fixture": true,
    "has_cadquery_import": true,
    "error_kind": "BRep_API"
  },
  {
    "reward_call": 69,
    "index": 1,
    "score": 0.76625,
    "task_id": "bike_accessory_mount_120n",
    "code_chars": 3653,
    "cadforge_build": 1.0,
    "cadforge_total": 0.725,
    "has_fixture": true,
    "has_cadquery_import": true,
    "error_kind": "build_ok"
  },
  {
    "reward_call": 69,
    "index": 2,
    "score": -0.875,
    "task_id": "folding_step_stool",
    "code_chars": 5125,
    "cadforge_build": 0.0,
    "cadforge_total": -1.0,
    "has_fixture": false,
    "has_cadquery_import": false,
    "error_kind": "ValueError"
  },
  {
    "reward_call": 69,
    "index": 3,
    "score": -0.84,
    "task_id": "folding_step_stool",
    "code_chars": 6132,
    "cadforge_build": 0.0,
    "cadforge_total": -1.0,
    "has_fixture": false,
    "has_cadquery_import": true,
    "error_kind": "SyntaxError"
  },
  {
    "reward_call": 70,
    "index": 0,
    "score": 0.7472510593220338,
    "task_id": "table_six_leg_500n",
    "code_chars": 4603,
    "cadforge_build": 1.0,
    "cadforge_total": 0.7026483050847457,
    "has_fixture": true,
    "has_cadquery_import": true,
    "error_kind": "build_ok"
  },
  {
    "reward_call": 70,
    "index": 1,
    "score": 0.8660160585254221,
    "task_id": "table_six_leg_500n",
    "code_chars": 3278,
    "cadforge_build": 1.0,
    "cadforge_total": 0.8423718335593201,
    "has_fixture": true,
    "has_cadquery_import": true,
    "error_kind": "build_ok"
  },
  {
    "reward_call": 70,
    "index": 2,
    "score": -0.79,
    "task_id": "ergonomic_curvy_chair_1000n",
    "code_chars": 4733,
    "cadforge_build": 0.0,
    "cadforge_total": -1.0,
    "has_fixture": false,
    "has_cadquery_import": true,
    "error_kind": "NameError"
  },
  {
    "reward_call": 70,
    "index": 3,
    "score": -0.84,
    "task_id": "ergonomic_curvy_chair_1000n",
    "code_chars": 4873,
    "cadforge_build": 0.0,
    "cadforge_total": -1.0,
    "has_fixture": false,
    "has_cadquery_import": true,
    "error_kind": "SyntaxError"
  },
  {
    "reward_call": 71,
    "index": 0,
    "score": -0.565,
    "task_id": "bench_vise_simplified",
    "code_chars": 4576,
    "cadforge_build": 0.0,
    "cadforge_total": -1.0,
    "has_fixture": true,
    "has_cadquery_import": true,
    "error_kind": "ValueError"
  },
  {
    "reward_call": 71,
    "index": 1,
    "score": 0.7258088453554393,
    "task_id": "bench_vise_simplified",
    "code_chars": 4090,
    "cadforge_build": 1.0,
    "cadforge_total": 0.6774221710063992,
    "has_fixture": true,
    "has_cadquery_import": true,
    "error_kind": "build_ok"
  },
  {
    "reward_call": 71,
    "index": 2,
    "score": -0.6649999999999999,
    "task_id": "drawer_handle_two_bolt",
    "code_chars": 2945,
    "cadforge_build": 0.0,
    "cadforge_total": -1.0,
    "has_fixture": true,
    "has_cadquery_import": true,
    "error_kind": "SyntaxError"
  },
  {
    "reward_call": 71,
    "index": 3,
    "score": -0.645,
    "task_id": "drawer_handle_two_bolt",
    "code_chars": 2655,
    "cadforge_build": 0.0,
    "cadforge_total": -1.0,
    "has_fixture": true,
    "has_cadquery_import": true,
    "error_kind": "NameError"
  },
  {
    "reward_call": 72,
    "index": 0,
    "score": -0.84,
    "task_id": "ergonomic_curvy_chair_1000n",
    "code_chars": 5184,
    "cadforge_build": 0.0,
    "cadforge_total": -1.0,
    "has_fixture": false,
    "has_cadquery_import": true,
    "error_kind": "SyntaxError"
  },
  {
    "reward_call": 72,
    "index": 1,
    "score": -0.84,
    "task_id": "ergonomic_curvy_chair_1000n",
    "code_chars": 5287,
    "cadforge_build": 0.0,
    "cadforge_total": -1.0,
    "has_fixture": false,
    "has_cadquery_import": true,
    "error_kind": "SyntaxError"
  },
  {
    "reward_call": 72,
    "index": 2,
    "score": -0.615,
    "task_id": "laptop_riser_vented",
    "code_chars": 4588,
    "cadforge_build": 0.0,
    "cadforge_total": -1.0,
    "has_fixture": true,
    "has_cadquery_import": true,
    "error_kind": "AttributeError"
  },
  {
    "reward_call": 72,
    "index": 3,
    "score": 0.8629728660675577,
    "task_id": "laptop_riser_vented",
    "code_chars": 3536,
    "cadforge_build": 1.0,
    "cadforge_total": 0.8387916071383033,
    "has_fixture": true,
    "has_cadquery_import": true,
    "error_kind": "build_ok"
  },
  {
    "reward_call": 73,
    "index": 0,
    "score": -0.6649999999999999,
    "task_id": "micro_drone_frame",
    "code_chars": 5797,
    "cadforge_build": 0.0,
    "cadforge_total": -1.0,
    "has_fixture": true,
    "has_cadquery_import": true,
    "error_kind": "SyntaxError"
  },
  {
    "reward_call": 73,
    "index": 1,
    "score": -0.84,
    "task_id": "micro_drone_frame",
    "code_chars": 5772,
    "cadforge_build": 0.0,
    "cadforge_total": -1.0,
    "has_fixture": false,
    "has_cadquery_import": true,
    "error_kind": "SyntaxError"
  },
  {
    "reward_call": 73,
    "index": 2,
    "score": 0.8132510351803028,
    "task_id": "bike_accessory_mount_120n",
    "code_chars": 5776,
    "cadforge_build": 1.0,
    "cadforge_total": 0.7802953355062386,
    "has_fixture": true,
    "has_cadquery_import": true,
    "error_kind": "build_ok"
  },
  {
    "reward_call": 73,
    "index": 3,
    "score": -0.565,
    "task_id": "bike_accessory_mount_120n",
    "code_chars": 5097,
    "cadforge_build": 0.0,
    "cadforge_total": -1.0,
    "has_fixture": true,
    "has_cadquery_import": true,
    "error_kind": "TypeError"
  },
  {
    "reward_call": 74,
    "index": 0,
    "score": 0.7389633309206752,
    "task_id": "desk_lamp_arm_joint",
    "code_chars": 5575,
    "cadforge_build": 1.0,
    "cadforge_total": 0.692898036377265,
    "has_fixture": true,
    "has_cadquery_import": true,
    "error_kind": "build_ok"
  },
  {
    "reward_call": 74,
    "index": 1,
    "score": -0.84,
    "task_id": "desk_lamp_arm_joint",
    "code_chars": 5890,
    "cadforge_build": 0.0,
    "cadforge_total": -1.0,
    "has_fixture": false,
    "has_cadquery_import": true,
    "error_kind": "SyntaxError"
  },
  {
    "reward_call": 74,
    "index": 2,
    "score": -0.595,
    "task_id": "hinge_leaf_barrel",
    "code_chars": 3936,
    "cadforge_build": 0.0,
    "cadforge_total": -1.0,
    "has_fixture": true,
    "has_cadquery_import": true,
    "error_kind": "TypeError"
  },
  {
    "reward_call": 74,
    "index": 3,
    "score": -0.595,
    "task_id": "hinge_leaf_barrel",
    "code_chars": 3966,
    "cadforge_build": 0.0,
    "cadforge_total": -1.0,
    "has_fixture": true,
    "has_cadquery_import": true,
    "error_kind": "TypeError"
  },
  {
    "reward_call": 75,
    "index": 0,
    "score": -0.84,
    "task_id": "gearbox_housing_split",
    "code_chars": 6076,
    "cadforge_build": 0.0,
    "cadforge_total": -1.0,
    "has_fixture": false,
    "has_cadquery_import": true,
    "error_kind": "SyntaxError"
  },
  {
    "reward_call": 75,
    "index": 1,
    "score": 0.8263909278635598,
    "task_id": "gearbox_housing_split",
    "code_chars": 5652,
    "cadforge_build": 1.0,
    "cadforge_total": 0.7957540327806586,
    "has_fixture": true,
    "has_cadquery_import": true,
    "error_kind": "build_ok"
  },
  {
    "reward_call": 75,
    "index": 2,
    "score": -0.645,
    "task_id": "pipe_clamp_saddle",
    "code_chars": 4730,
    "cadforge_build": 0.0,
    "cadforge_total": -1.0,
    "has_fixture": true,
    "has_cadquery_import": true,
    "error_kind": "AttributeError"
  },
  {
    "reward_call": 75,
    "index": 3,
    "score": -0.615,
    "task_id": "pipe_clamp_saddle",
    "code_chars": 4192,
    "cadforge_build": 0.0,
    "cadforge_total": -1.0,
    "has_fixture": true,
    "has_cadquery_import": true,
    "error_kind": "NameError"
  },
  {
    "reward_call": 76,
    "index": 0,
    "score": 0.6222121869979141,
    "task_id": "wall_j_hook_120n",
    "code_chars": 2305,
    "cadforge_build": 1.0,
    "cadforge_total": 0.5555437494093108,
    "has_fixture": true,
    "has_cadquery_import": true,
    "error_kind": "build_ok"
  },
  {
    "reward_call": 76,
    "index": 1,
    "score": -0.565,
    "task_id": "wall_j_hook_120n",
    "code_chars": 3598,
    "cadforge_build": 0.0,
    "cadforge_total": -1.0,
    "has_fixture": true,
    "has_cadquery_import": true,
    "error_kind": "unknown"
  },
  {
    "reward_call": 76,
    "index": 2,
    "score": 0.7234843750000001,
    "task_id": "robot_gripper_two_finger",
    "code_chars": 3930,
    "cadforge_build": 1.0,
    "cadforge_total": 0.6746875000000001,
    "has_fixture": true,
    "has_cadquery_import": true,
    "error_kind": "build_ok"
  },
  {
    "reward_call": 76,
    "index": 3,
    "score": 0.7888723958333335,
    "task_id": "robot_gripper_two_finger",
    "code_chars": 3039,
    "cadforge_build": 1.0,
    "cadforge_total": 0.7516145833333334,
    "has_fixture": true,
    "has_cadquery_import": true,
    "error_kind": "build_ok"
  },
  {
    "reward_call": 77,
    "index": 0,
    "score": 0.8540833333333334,
    "task_id": "table_six_leg_500n",
    "code_chars": 5750,
    "cadforge_build": 1.0,
    "cadforge_total": 0.8283333333333334,
    "has_fixture": true,
    "has_cadquery_import": true,
    "error_kind": "build_ok"
  },
  {
    "reward_call": 77,
    "index": 1,
    "score": 0.8546711906033754,
    "task_id": "table_six_leg_500n",
    "code_chars": 3273,
    "cadforge_build": 1.0,
    "cadforge_total": 0.829024930121618,
    "has_fixture": true,
    "has_cadquery_import": true,
    "error_kind": "build_ok"
  },
  {
    "reward_call": 77,
    "index": 2,
    "score": -0.695,
    "task_id": "lightweight_truss_support_250n",
    "code_chars": 4610,
    "cadforge_build": 0.0,
    "cadforge_total": -1.0,
    "has_fixture": true,
    "has_cadquery_import": true,
    "error_kind": "SyntaxError"
  },
  {
    "reward_call": 77,
    "index": 3,
    "score": -0.565,
    "task_id": "lightweight_truss_support_250n",
    "code_chars": 4999,
    "cadforge_build": 0.0,
    "cadforge_total": -1.0,
    "has_fixture": true,
    "has_cadquery_import": true,
    "error_kind": "ValueError"
  },
  {
    "reward_call": 78,
    "index": 0,
    "score": 0.7214649946671322,
    "task_id": "shaft_torque_clamp_120nm",
    "code_chars": 4041,
    "cadforge_build": 1.0,
    "cadforge_total": 0.6723117584319203,
    "has_fixture": true,
    "has_cadquery_import": true,
    "error_kind": "build_ok"
  },
  {
    "reward_call": 78,
    "index": 1,
    "score": 0.6966119958133985,
    "task_id": "shaft_torque_clamp_120nm",
    "code_chars": 2833,
    "cadforge_build": 1.0,
    "cadforge_total": 0.6430729362510571,
    "has_fixture": true,
    "has_cadquery_import": true,
    "error_kind": "build_ok"
  },
  {
    "reward_call": 78,
    "index": 2,
    "score": -0.6649999999999999,
    "task_id": "bottle_cage_bike",
    "code_chars": 4702,
    "cadforge_build": 0.0,
    "cadforge_total": -1.0,
    "has_fixture": true,
    "has_cadquery_import": true,
    "error_kind": "SyntaxError"
  },
  {
    "reward_call": 78,
    "index": 3,
    "score": -0.615,
    "task_id": "bottle_cage_bike",
    "code_chars": 5633,
    "cadforge_build": 0.0,
    "cadforge_total": -1.0,
    "has_fixture": true,
    "has_cadquery_import": true,
    "error_kind": "NameError"
  },
  {
    "reward_call": 79,
    "index": 0,
    "score": 0.7213078184926907,
    "task_id": "cable_clip_snap",
    "code_chars": 3680,
    "cadforge_build": 1.0,
    "cadforge_total": 0.6721268452855184,
    "has_fixture": true,
    "has_cadquery_import": true,
    "error_kind": "build_ok"
  },
  {
    "reward_call": 79,
    "index": 1,
    "score": -0.615,
    "task_id": "cable_clip_snap",
    "code_chars": 5223,
    "cadforge_build": 0.0,
    "cadforge_total": -1.0,
    "has_fixture": true,
    "has_cadquery_import": true,
    "error_kind": "AttributeError"
  },
  {
    "reward_call": 79,
    "index": 2,
    "score": 0.9192936698617971,
    "task_id": "phone_stand_adjustable_hinge",
    "code_chars": 4126,
    "cadforge_build": 1.0,
    "cadforge_total": 0.9050513763079966,
    "has_fixture": true,
    "has_cadquery_import": true,
    "error_kind": "build_ok"
  },
  {
    "reward_call": 79,
    "index": 3,
    "score": 0.7875,
    "task_id": "phone_stand_adjustable_hinge",
    "code_chars": 3566,
    "cadforge_build": 1.0,
    "cadforge_total": 0.75,
    "has_fixture": true,
    "has_cadquery_import": true,
    "error_kind": "build_ok"
  },
  {
    "reward_call": 80,
    "index": 0,
    "score": 0.736593127816838,
    "task_id": "shelf_bracket_triangular_200n",
    "code_chars": 5101,
    "cadforge_build": 1.0,
    "cadforge_total": 0.6901095621374563,
    "has_fixture": true,
    "has_cadquery_import": true,
    "error_kind": "build_ok"
  },
  {
    "reward_call": 80,
    "index": 1,
    "score": -0.615,
    "task_id": "shelf_bracket_triangular_200n",
    "code_chars": 2796,
    "cadforge_build": 0.0,
    "cadforge_total": -1.0,
    "has_fixture": true,
    "has_cadquery_import": true,
    "error_kind": "AttributeError"
  },
  {
    "reward_call": 80,
    "index": 2,
    "score": -0.84,
    "task_id": "folding_step_stool",
    "code_chars": 5352,
    "cadforge_build": 0.0,
    "cadforge_total": -1.0,
    "has_fixture": false,
    "has_cadquery_import": true,
    "error_kind": "SyntaxError"
  },
  {
    "reward_call": 80,
    "index": 3,
    "score": -0.84,
    "task_id": "folding_step_stool",
    "code_chars": 5373,
    "cadforge_build": 0.0,
    "cadforge_total": -1.0,
    "has_fixture": false,
    "has_cadquery_import": true,
    "error_kind": "SyntaxError"
  }
]